{
  "brand": "Honda",
  "brandImage": "https://p1-dcd.byteimg.com/img/tos-cn-i-dcdx/ce848b3a359d48ee97a3ffbc79c99aa8~tplv-resize:0:0.png",
  "cars": [
    {
      "carName": "奥德赛",
      "mainImage": "https://p3.dcarimg.com/img/tos-cn-i-dcdx/d9fe9c6614624acd92c3c1d16bc68f1d~1200x0.png",
      "configs": [
        {
          "configName": "奥德赛 2024款 2.0L 锐·悦享版",
          "price": "23.58万",
          "fuelType": "油电混合",
          "size": "4861x1820x1712",
          "manufacturer": "广汽本田",
          "class": "中型MPV",
          "power": "混合动力 184马力"
        },
        {
          "configName": "奥德赛 2024款 2.0L 锐·智享版",
          "price": "27.58万",
          "fuelType": "油电混合",
          "size": "4861x1820x1712",
          "manufacturer": "广汽本田",
          "class": "中型MPV",
          "power": "混合动力 184马力"
        },
        {
          "configName": "奥德赛 2024款 2.0L 锐·领享版",
          "price": "28.58万",
          "fuelType": "油电混合",
          "size": "4861x1820x1712",
          "manufacturer": "广汽本田",
          "class": "中型MPV",
          "power": "混合动力 184马力"
        },
        {
          "configName": "奥德赛 2024款 2.0L 锐·耀享版",
          "price": "29.98万",
          "fuelType": "油电混合",
          "size": "4861x1820x1712",
          "manufacturer": "广汽本田",
          "class": "中型MPV",
          "power": "混合动力 184马力"
        },
        {
          "configName": "奥德赛 2024款 2.0L 锐·至尊版",
          "price": "32.88万",
          "fuelType": "油电混合",
          "size": "4861x1820x1712",
          "manufacturer": "广汽本田",
          "class": "中型MPV",
          "power": "混合动力 184马力"
        },
        {
          "configName": "奥德赛 2024款 2.0L 锐·领享福祉版",
          "price": "34.08万",
          "fuelType": "油电混合",
          "size": "4861x1820x1712",
          "manufacturer": "广汽本田",
          "class": "中型MPV",
          "power": "混合动力 184马力"
        },
        {
          "configName": "奥德赛 2024款 2.0L 锐·御享四座版",
          "price": "43.98万",
          "fuelType": "油电混合",
          "size": "4861x1820x1705",
          "manufacturer": "广汽本田",
          "class": "中型MPV",
          "power": "混合动力 184马力"
        }
      ]
    },
    {
      "carName": "雅阁",
      "mainImage": "https://p3.dcarimg.com/img/tos-cn-i-dcdx/d21dcad12dfa49e3abb1c42cad487941~1200x0.png",
      "configs": [
        {
          "configName": "雅阁 2025款 运动系列 锐·T动 260TURBO 舒适版",
          "price": "17.98万",
          "fuelType": "汽油",
          "size": "4990x1862x1449",
          "manufacturer": "广汽本田",
          "class": "中型车",
          "power": "1.5T 192马力 L4"
        },
        {
          "configName": "雅阁 2025款 运动系列 锐·T动 260TURBO 豪华版",
          "price": "19.78万",
          "fuelType": "汽油",
          "size": "4990x1862x1449",
          "manufacturer": "广汽本田",
          "class": "中型车",
          "power": "1.5T 192马力 L4"
        },
        {
          "configName": "雅阁 2025款 运动系列 锐·T动 260TURBO 尊贵版",
          "price": "21.48万",
          "fuelType": "汽油",
          "size": "4990x1862x1449",
          "manufacturer": "广汽本田",
          "class": "中型车",
          "power": "1.5T 192马力 L4"
        },
        {
          "configName": "雅阁 2025款 锐·T动 260TURBO 舒适版",
          "price": "17.98万",
          "fuelType": "汽油",
          "size": "4980x1862x1449",
          "manufacturer": "广汽本田",
          "class": "中型车",
          "power": "1.5T 192马力 L4"
        },
        {
          "configName": "雅阁 2025款 锐·T动 260TURBO 豪华版",
          "price": "19.78万",
          "fuelType": "汽油",
          "size": "4980x1862x1449",
          "manufacturer": "广汽本田",
          "class": "中型车",
          "power": "1.5T 192马力 L4"
        },
        {
          "configName": "雅阁 2025款 锐·T动 260TURBO 尊贵版",
          "price": "21.48万",
          "fuelType": "汽油",
          "size": "4980x1862x1449",
          "manufacturer": "广汽本田",
          "class": "中型车",
          "power": "1.5T 192马力 L4"
        },
        {
          "configName": "雅阁 2025款 锐·T动 260TURBO 旗舰版",
          "price": "23.88万",
          "fuelType": "汽油",
          "size": "4980x1862x1449",
          "manufacturer": "广汽本田",
          "class": "中型车",
          "power": "1.5T 192马力 L4"
        }
      ]
    },
    {
      "carName": "飞度",
      "mainImage": "https://p3.dcarimg.com/img/tos-cn-i-dcdx/364fd0eb7e3949fabae8234c84a77a54~1200x0.png",
      "configs": [
        {
          "configName": "飞度 2024款 1.5L CVT  無限MUGEN版",
          "price": "9.78万",
          "fuelType": "汽油",
          "size": "4125x1694x1537",
          "manufacturer": "广汽本田",
          "class": "小型车",
          "power": "1.5L 124马力 L4"
        },
        {
          "configName": "飞度 2023款 1.5L CVT潮享版",
          "price": "8.68万",
          "fuelType": "汽油",
          "size": "4109x1694x1537",
          "manufacturer": "广汽本田",
          "class": "小型车",
          "power": "1.5L 124马力 L4"
        },
        {
          "configName": "飞度 2023款 1.5L CVT潮跑版",
          "price": "9.68万",
          "fuelType": "汽油",
          "size": "4081x1694x1537",
          "manufacturer": "广汽本田",
          "class": "小型车",
          "power": "1.5L 124马力 L4"
        },
        {
          "configName": "飞度 2023款 1.5L CVT潮跑Pro版",
          "price": "10.78万",
          "fuelType": "汽油",
          "size": "4081x1694x1537",
          "manufacturer": "广汽本田",
          "class": "小型车",
          "power": "1.5L 124马力 L4"
        },
        {
          "configName": "飞度 2023款 1.5L CVT潮越版",
          "price": "10.08万",
          "fuelType": "汽油",
          "size": "4095x1725x1567",
          "manufacturer": "广汽本田",
          "class": "小型车",
          "power": "1.5L 124马力 L4"
        },
        {
          "configName": "飞度 2023款 1.5L CVT潮越Max版",
          "price": "10.88万",
          "fuelType": "汽油",
          "size": "4095x1725x1567",
          "manufacturer": "广汽本田",
          "class": "小型车",
          "power": "1.5L 124马力 L4"
        }
      ]
    },
    {
      "carName": "LIFE",
      "mainImage": "https://p3.dcarimg.com/img/tos-cn-i-dcdx/f276329ea9d04596a263f83b009f41b0~1200x0.png",
      "configs": [
        {
          "configName": "本田LIFE 2023款 1.5L CVT SPORT心动版",
          "price": "9.78万",
          "fuelType": "汽油",
          "size": "4109x1694x1537",
          "manufacturer": "东风本田",
          "class": "小型车",
          "power": "1.5L 124马力 L4"
        },
        {
          "configName": "本田LIFE 2023款 1.5L CVT SPO-SS灵动版",
          "price": "10.88万",
          "fuelType": "汽油",
          "size": "4109x1694x1537",
          "manufacturer": "东风本田",
          "class": "小型车",
          "power": "1.5L 124马力 L4"
        },
        {
          "configName": "本田LIFE 2023款 1.5L CVT CRO-S乐趣版",
          "price": "10.28万",
          "fuelType": "汽油",
          "size": "4111x1725x1567",
          "manufacturer": "东风本田",
          "class": "小型车",
          "power": "1.5L 124马力 L4"
        },
        {
          "configName": "本田LIFE 2023款 1.5L CVT CRO-SS灵趣版",
          "price": "11.28万",
          "fuelType": "汽油",
          "size": "4111x1725x1567",
          "manufacturer": "东风本田",
          "class": "小型车",
          "power": "1.5L 124马力 L4"
        }
      ]
    },
    {
      "carName": "凌派",
      "mainImage": "https://p3.dcarimg.com/img/tos-cn-i-dcdx/d6ca2a9cb1974c1a91877801929b58ad~1200x0.png",
      "configs": [
        {
          "configName": "凌派 2024款 180Turbo CVT豪华版",
          "price": "11.98万",
          "fuelType": "汽油",
          "size": "4766x1804x1509",
          "manufacturer": "广汽本田",
          "class": "紧凑型车",
          "power": "1.0T 122马力 L3"
        },
        {
          "configName": "凌派 2024款 180Turbo CVT智享版",
          "price": "12.68万",
          "fuelType": "汽油",
          "size": "4766x1804x1509",
          "manufacturer": "广汽本田",
          "class": "紧凑型车",
          "power": "1.0T 122马力 L3"
        },
        {
          "configName": "凌派 2024款 180Turbo CVT旗舰版",
          "price": "13.98万",
          "fuelType": "汽油",
          "size": "4766x1804x1509",
          "manufacturer": "广汽本田",
          "class": "紧凑型车",
          "power": "1.0T 122马力 L3"
        },
        {
          "configName": "凌派 2024款 1.5L 锐·豪华版",
          "price": "14.98万",
          "fuelType": "油电混合",
          "size": "4766x1804x1509",
          "manufacturer": "广汽本田",
          "class": "紧凑型车",
          "power": "混合动力 131马力"
        },
        {
          "configName": "凌派 2024款 1.5L 锐·智享版",
          "price": "15.58万",
          "fuelType": "油电混合",
          "size": "4766x1804x1509",
          "manufacturer": "广汽本田",
          "class": "紧凑型车",
          "power": "混合动力 131马力"
        },
        {
          "configName": "凌派 2024款 1.5L 锐·旗舰版",
          "price": "16.98万",
          "fuelType": "油电混合",
          "size": "4766x1804x1509",
          "manufacturer": "广汽本田",
          "class": "紧凑型车",
          "power": "混合动力 131马力"
        }
      ]
    },
    {
      "carName": "思域(进口)",
      "mainImage": "https://p3.dcarimg.com/img/tos-cn-i-dcdx/8ca311d5485f45b9b973ed04664e36f6~1200x0.png",
      "configs": [
        {
          "configName": "思域(进口) 2023款 420TURBO TYPE R",
          "price": "42万",
          "fuelType": "汽油",
          "size": "4595x1890x1405",
          "manufacturer": "本田(进口)",
          "class": "紧凑型车",
          "power": "2.0T 300马力 L4"
        }
      ]
    },
    {
      "carName": "享域",
      "mainImage": "https://p3.dcarimg.com/img/tos-cn-i-dcdx/01ad2bfb9f24451ba22e22a86fdf86b9~1200x0.png",
      "configs": [
        {
          "configName": "享域 2022款 180Turbo CVT畅享版",
          "price": "10.98万",
          "fuelType": "汽油",
          "size": "4772x1804x1509",
          "manufacturer": "东风本田",
          "class": "紧凑型车",
          "power": "1.0T 122马力 L3"
        },
        {
          "configName": "享域 2022款 180Turbo CVT舒享版",
          "price": "11.98万",
          "fuelType": "汽油",
          "size": "4772x1804x1509",
          "manufacturer": "东风本田",
          "class": "紧凑型车",
          "power": "1.0T 122马力 L3"
        },
        {
          "configName": "享域 2022款 180Turbo CVT乐享版",
          "price": "12.78万",
          "fuelType": "汽油",
          "size": "4772x1804x1509",
          "manufacturer": "东风本田",
          "class": "紧凑型车",
          "power": "1.0T 122马力 L3"
        },
        {
          "configName": "享域 2022款 180Turbo CVT耀享版",
          "price": "13.98万",
          "fuelType": "汽油",
          "size": "4772x1804x1509",
          "manufacturer": "东风本田",
          "class": "紧凑型车",
          "power": "1.0T 122马力 L3"
        },
        {
          "configName": "享域 2022款 锐·混动 1.5L 净适版",
          "price": "13.99万",
          "fuelType": "油电混合",
          "size": "4772x1804x1509",
          "manufacturer": "东风本田",
          "class": "紧凑型车",
          "power": "混合动力 131马力"
        },
        {
          "configName": "享域 2022款 锐·混动 1.5L 净畅版",
          "price": "14.99万",
          "fuelType": "油电混合",
          "size": "4772x1804x1509",
          "manufacturer": "东风本田",
          "class": "紧凑型车",
          "power": "混合动力 131马力"
        },
        {
          "configName": "享域 2022款 锐·混动 1.5L 净享版",
          "price": "16.29万",
          "fuelType": "油电混合",
          "size": "4772x1804x1509",
          "manufacturer": "东风本田",
          "class": "紧凑型车",
          "power": "混合动力 131马力"
        },
        {
          "configName": "享域 2022款 锐·混动 1.5L 净耀版",
          "price": "16.99万",
          "fuelType": "油电混合",
          "size": "4772x1804x1509",
          "manufacturer": "东风本田",
          "class": "紧凑型车",
          "power": "混合动力 131马力"
        }
      ]
    },
    {
      "carName": "思域",
      "mainImage": "https://p3.dcarimg.com/img/tos-cn-i-dcdx/e8b217f0e87d4b5aadb1582680422a76~1200x0.png",
      "configs": [
        {
          "configName": "思域 2025款 180TURBO CVT 智趣",
          "price": "12.99万",
          "fuelType": "汽油",
          "size": "4685x1802x1415",
          "manufacturer": "东风本田",
          "class": "紧凑型车",
          "power": "1.5T 129马力 L4"
        },
        {
          "configName": "思域 2025款 240TURBO CVT 智趣Plus",
          "price": "13.99万",
          "fuelType": "汽油",
          "size": "4685x1802x1415",
          "manufacturer": "东风本田",
          "class": "紧凑型车",
          "power": "1.5T 182马力 L4"
        },
        {
          "configName": "思域 2025款 240TURBO CVT 智趣Pro",
          "price": "14.59万",
          "fuelType": "汽油",
          "size": "4685x1802x1415",
          "manufacturer": "东风本田",
          "class": "紧凑型车",
          "power": "1.5T 182马力 L4"
        },
        {
          "configName": "思域 2025款 240TURBO CVT 智趣Max",
          "price": "15.99万",
          "fuelType": "汽油",
          "size": "4685x1802x1420",
          "manufacturer": "东风本田",
          "class": "紧凑型车",
          "power": "1.5T 182马力 L4"
        },
        {
          "configName": "思域 2025款 2.0L e:HEV 混动",
          "price": "13.99万",
          "fuelType": "油电混合",
          "size": "4685x1802x1415",
          "manufacturer": "东风本田",
          "class": "紧凑型车",
          "power": "混合动力 184马力"
        },
        {
          "configName": "思域 2025款 2.0L e:HEV 混动Plus",
          "price": "14.99万",
          "fuelType": "油电混合",
          "size": "4685x1802x1415",
          "manufacturer": "东风本田",
          "class": "紧凑型车",
          "power": "混合动力 184马力"
        },
        {
          "configName": "思域 2025款 2.0L e:HEV 混动Pro",
          "price": "16.39万",
          "fuelType": "油电混合",
          "size": "4685x1802x1415",
          "manufacturer": "东风本田",
          "class": "紧凑型车",
          "power": "混合动力 184马力"
        },
        {
          "configName": "思域 2025款 2.0L e:HEV 混动Max",
          "price": "17.79万",
          "fuelType": "油电混合",
          "size": "4685x1802x1420",
          "manufacturer": "东风本田",
          "class": "紧凑型车",
          "power": "混合动力 184马力"
        },
        {
          "configName": "思域 2023款 HATCHBACK 240TURBO CVT极跃版",
          "price": "14.59万",
          "fuelType": "汽油",
          "size": "4548x1802x1415",
          "manufacturer": "东风本田",
          "class": "紧凑型车",
          "power": "1.5T 182马力 L4"
        },
        {
          "configName": "思域 2023款 HATCHBACK 240TURBO CVT极锐版",
          "price": "15.39万",
          "fuelType": "汽油",
          "size": "4548x1802x1415",
          "manufacturer": "东风本田",
          "class": "紧凑型车",
          "power": "1.5T 182马力 L4"
        },
        {
          "configName": "思域 2023款 HATCHBACK 240TURBO 手动极劲版",
          "price": "15.99万",
          "fuelType": "汽油",
          "size": "4548x1802x1420",
          "manufacturer": "东风本田",
          "class": "紧凑型车",
          "power": "1.5T 182马力 L4"
        },
        {
          "configName": "思域 2023款 HATCHBACK 240TURBO CVT极锋版",
          "price": "16.99万",
          "fuelType": "汽油",
          "size": "4548x1802x1420",
          "manufacturer": "东风本田",
          "class": "紧凑型车",
          "power": "1.5T 182马力 L4"
        },
        {
          "configName": "思域 2023款 HATCHBACK 2.0L e:HEV 极曜版",
          "price": "16.99万",
          "fuelType": "油电混合",
          "size": "4548x1802x1415",
          "manufacturer": "东风本田",
          "class": "紧凑型车",
          "power": "油电混合 184马力"
        },
        {
          "configName": "思域 2023款 HATCHBACK 2.0L e:HEV 极控版",
          "price": "17.99万",
          "fuelType": "油电混合",
          "size": "4548x1802x1420",
          "manufacturer": "东风本田",
          "class": "紧凑型车",
          "power": "油电混合 184马力"
        },
        {
          "configName": "思域 2022款 180TURBO CVT尚动版",
          "price": "12.99万",
          "fuelType": "汽油",
          "size": "4674x1802x1415",
          "manufacturer": "东风本田",
          "class": "紧凑型车",
          "power": "1.5T 129马力 L4"
        },
        {
          "configName": "思域 2022款 180TURBO CVT尚擎版",
          "price": "13.69万",
          "fuelType": "汽油",
          "size": "4674x1802x1415",
          "manufacturer": "东风本田",
          "class": "紧凑型车",
          "power": "1.5T 129马力 L4"
        },
        {
          "configName": "思域 2022款 240TURBO CVT劲动版",
          "price": "14.29万",
          "fuelType": "汽油",
          "size": "4674x1802x1415",
          "manufacturer": "东风本田",
          "class": "紧凑型车",
          "power": "1.5T 182马力 L4"
        },
        {
          "configName": "思域 2022款 240TURBO CVT燃动版",
          "price": "14.99万",
          "fuelType": "汽油",
          "size": "4674x1802x1415",
          "manufacturer": "东风本田",
          "class": "紧凑型车",
          "power": "1.5T 182马力 L4"
        },
        {
          "configName": "思域 2022款 240TURBO CVT劲控版",
          "price": "15.89万",
          "fuelType": "汽油",
          "size": "4674x1802x1415",
          "manufacturer": "东风本田",
          "class": "紧凑型车",
          "power": "1.5T 182马力 L4"
        },
        {
          "configName": "思域 2022款 2.0L e:HEV 先锋版",
          "price": "15.99万",
          "fuelType": "油电混合",
          "size": "4674x1802x1415",
          "manufacturer": "东风本田",
          "class": "紧凑型车",
          "power": "混合动力 184马力"
        },
        {
          "configName": "思域 2022款 2.0L e:HEV 锐力版",
          "price": "17.39万",
          "fuelType": "油电混合",
          "size": "4674x1802x1415",
          "manufacturer": "东风本田",
          "class": "紧凑型车",
          "power": "混合动力 184马力"
        },
        {
          "configName": "思域 2022款 2.0L e:HEV 劲速版",
          "price": "18.79万",
          "fuelType": "油电混合",
          "size": "4674x1802x1420",
          "manufacturer": "东风本田",
          "class": "紧凑型车",
          "power": "混合动力 184马力"
        }
      ]
    },
    {
      "carName": "广汽本田GT",
      "mainImage": "https://p3.dcarimg.com/img/tos-cn-i-dcdx/994a45604d1945d6ba930b7870be7e3c~1200x0.png",
      "configs": []
    },
    {
      "carName": "东风本田GT",
      "mainImage": "https://p3.dcarimg.com/img/tos-cn-i-dcdx/a223ac1e4c6142ddbfb3e6cdf6afd598~1200x0.png",
      "configs": []
    },
    {
      "carName": "型格",
      "mainImage": "https://p3.dcarimg.com/img/tos-cn-i-dcdx/10a0f7d8398e457b9c31b70e8b5cd85d~1200x0.png",
      "configs": [
        {
          "configName": "型格 2025款 2.0L e:HEV 锐·先锋版",
          "price": "13.99万",
          "fuelType": "油电混合",
          "size": "4689x1802x1415",
          "manufacturer": "广汽本田",
          "class": "紧凑型车",
          "power": "油电混合 184马力"
        },
        {
          "configName": "型格 2025款 2.0L e:HEV 锐·科技版",
          "price": "15.29万",
          "fuelType": "油电混合",
          "size": "4689x1802x1415",
          "manufacturer": "广汽本田",
          "class": "紧凑型车",
          "power": "油电混合 184马力"
        },
        {
          "configName": "型格 2025款 HATCHBACK 2.0L e:HEV 锐·舒享型酷套装",
          "price": "17.09万",
          "fuelType": "油电混合",
          "size": "4563x1802x1420",
          "manufacturer": "广汽本田",
          "class": "紧凑型车",
          "power": "油电混合 184马力"
        },
        {
          "configName": "型格 2025款 240TURBO MT极速版",
          "price": "12.99万",
          "fuelType": "汽油",
          "size": "4689x1802x1415",
          "manufacturer": "广汽本田",
          "class": "紧凑型车",
          "power": "1.5T 182马力 L4"
        },
        {
          "configName": "型格 2025款 240TURBO CVT科技版",
          "price": "13.99万",
          "fuelType": "汽油",
          "size": "4689x1802x1415",
          "manufacturer": "广汽本田",
          "class": "紧凑型车",
          "power": "1.5T 182马力 L4"
        },
        {
          "configName": "型格 2025款 HATCHBACK 240TURBO MT极速版",
          "price": "13.99万",
          "fuelType": "汽油",
          "size": "4563x1802x1415",
          "manufacturer": "广汽本田",
          "class": "紧凑型车",
          "power": "1.5T 182马力 L4"
        },
        {
          "configName": "型格 2025款 HATCHBACK 240TURBO MT冠军版",
          "price": "16.19万",
          "fuelType": "汽油",
          "size": "4563x1802x1420",
          "manufacturer": "广汽本田",
          "class": "紧凑型车",
          "power": "1.5T 182马力 L4"
        },
        {
          "configName": "型格 2024款 240TURBO  無限MUGEN版",
          "price": "15.79万",
          "fuelType": "汽油",
          "size": "4702x1802x1415",
          "manufacturer": "广汽本田",
          "class": "紧凑型车",
          "power": "1.5T 182马力 L4"
        },
        {
          "configName": "型格 2023款 HATCHBACK 240TURBO 专属MT版",
          "price": "13.99万",
          "fuelType": "汽油",
          "size": "4563x1802x1415",
          "manufacturer": "广汽本田",
          "class": "紧凑型车",
          "power": "1.5T 182马力 L4"
        },
        {
          "configName": "型格 2023款 HATCHBACK 240TURBO CVT领潮版",
          "price": "14.89万",
          "fuelType": "汽油",
          "size": "4563x1802x1415",
          "manufacturer": "广汽本田",
          "class": "紧凑型车",
          "power": "1.5T 182马力 L4"
        },
        {
          "configName": "型格 2023款 HATCHBACK 240TURBO CVT幻夜·豪华版",
          "price": "15.89万",
          "fuelType": "汽油",
          "size": "4563x1802x1420",
          "manufacturer": "广汽本田",
          "class": "紧凑型车",
          "power": "1.5T 182马力 L4"
        },
        {
          "configName": "型格 2023款 HATCHBACK 240TURBO CVT幻夜·尊享版",
          "price": "17.19万",
          "fuelType": "汽油",
          "size": "4563x1802x1420",
          "manufacturer": "广汽本田",
          "class": "紧凑型车",
          "power": "1.5T 182马力 L4"
        },
        {
          "configName": "型格 2023款 HATCHBACK 2.0L e:HEV 锐·领潮版",
          "price": "16.99万",
          "fuelType": "油电混合",
          "size": "4563x1802x1415",
          "manufacturer": "广汽本田",
          "class": "紧凑型车",
          "power": "油电混合 184马力"
        },
        {
          "configName": "型格 2023款 HATCHBACK 2.0L e:HEV 锐·豪华版",
          "price": "18.29万",
          "fuelType": "油电混合",
          "size": "4563x1802x1420",
          "manufacturer": "广汽本田",
          "class": "紧凑型车",
          "power": "油电混合 184马力"
        },
        {
          "configName": "型格 2023款 240TURBO 专属MT版",
          "price": "12.99万",
          "fuelType": "汽油",
          "size": "4689x1802x1415",
          "manufacturer": "广汽本田",
          "class": "紧凑型车",
          "power": "1.5T 182马力 L4"
        },
        {
          "configName": "型格 2023款 240TURBO CVT领先版",
          "price": "14.19万",
          "fuelType": "汽油",
          "size": "4689x1802x1415",
          "manufacturer": "广汽本田",
          "class": "紧凑型车",
          "power": "1.5T 182马力 L4"
        },
        {
          "configName": "型格 2023款 240TURBO CVT科技版",
          "price": "14.29万",
          "fuelType": "汽油",
          "size": "4689x1802x1415",
          "manufacturer": "广汽本田",
          "class": "紧凑型车",
          "power": "1.5T 182马力 L4"
        },
        {
          "configName": "型格 2023款 240TURBO CVT幻夜·科技版",
          "price": "14.99万",
          "fuelType": "汽油",
          "size": "4689x1802x1415",
          "manufacturer": "广汽本田",
          "class": "紧凑型车",
          "power": "1.5T 182马力 L4"
        },
        {
          "configName": "型格 2023款 240TURBO CVT智享版",
          "price": "15.19万",
          "fuelType": "汽油",
          "size": "4689x1802x1415",
          "manufacturer": "广汽本田",
          "class": "紧凑型车",
          "power": "1.5T 182马力 L4"
        },
        {
          "configName": "型格 2023款 240TURBO CVT豪华版",
          "price": "15.29万",
          "fuelType": "汽油",
          "size": "4689x1802x1415",
          "manufacturer": "广汽本田",
          "class": "紧凑型车",
          "power": "1.5T 182马力 L4"
        },
        {
          "configName": "型格 2023款 240TURBO CVT幻夜·豪华版",
          "price": "15.79万",
          "fuelType": "汽油",
          "size": "4689x1802x1420",
          "manufacturer": "广汽本田",
          "class": "紧凑型车",
          "power": "1.5T 182马力 L4"
        },
        {
          "configName": "型格 2023款 240TURBO CVT尊享版",
          "price": "16.69万",
          "fuelType": "汽油",
          "size": "4689x1802x1420",
          "manufacturer": "广汽本田",
          "class": "紧凑型车",
          "power": "1.5T 182马力 L4"
        },
        {
          "configName": "型格 2023款 2.0L e:HEV 锐·科技版",
          "price": "16.39万",
          "fuelType": "油电混合",
          "size": "4689x1802x1415",
          "manufacturer": "广汽本田",
          "class": "紧凑型车",
          "power": "油电混合 184马力"
        },
        {
          "configName": "型格 2023款 2.0L e:HEV 锐·豪华版",
          "price": "17.79万",
          "fuelType": "油电混合",
          "size": "4689x1802x1420",
          "manufacturer": "广汽本田",
          "class": "紧凑型车",
          "power": "油电混合 184马力"
        },
        {
          "configName": "型格 2023款 2.0L e:HEV 锐·尊享版",
          "price": "18.69万",
          "fuelType": "油电混合",
          "size": "4689x1802x1420",
          "manufacturer": "广汽本田",
          "class": "紧凑型车",
          "power": "油电混合 184马力"
        }
      ]
    },
    {
      "carName": "雅阁 PHEV",
      "mainImage": "https://p3.dcarimg.com/img/tos-cn-i-dcdx/84b81f70f86c4d05a52e1aa6e3e25826~1200x0.png",
      "configs": [
        {
          "configName": "雅阁 PHEV 2025款 e:PHEV 豪华版",
          "price": "22.68万",
          "fuelType": "插电式混合动力",
          "size": "4980x1862x1449",
          "manufacturer": "广汽本田",
          "class": "中型车",
          "power": "插电式混动 184马力"
        },
        {
          "configName": "雅阁 PHEV 2025款 e:PHEV 尊贵版",
          "price": "23.88万",
          "fuelType": "插电式混合动力",
          "size": "4980x1862x1449",
          "manufacturer": "广汽本田",
          "class": "中型车",
          "power": "插电式混动 184马力"
        },
        {
          "configName": "雅阁 PHEV 2025款 e:PHEV 旗舰版",
          "price": "26.88万",
          "fuelType": "插电式混合动力",
          "size": "4980x1862x1449",
          "manufacturer": "广汽本田",
          "class": "中型车",
          "power": "插电式混动 184马力"
        },
        {
          "configName": "雅阁 PHEV 2024款 e:PHEV 豪华版",
          "price": "22.68万",
          "fuelType": "插电式混合动力",
          "size": "4980x1862x1449",
          "manufacturer": "广汽本田",
          "class": "中型车",
          "power": "插电式混动 184马力"
        },
        {
          "configName": "雅阁 PHEV 2023款 e:PHEV 智享版",
          "price": "22.58万",
          "fuelType": "插电式混合动力",
          "size": "4980x1862x1449",
          "manufacturer": "广汽本田",
          "class": "中型车",
          "power": "插电式混动 184马力"
        },
        {
          "configName": "雅阁 PHEV 2023款 e:PHEV 尊贵版",
          "price": "23.88万",
          "fuelType": "插电式混合动力",
          "size": "4980x1862x1449",
          "manufacturer": "广汽本田",
          "class": "中型车",
          "power": "插电式混动 184马力"
        },
        {
          "configName": "雅阁 PHEV 2023款 e:PHEV 旗舰版",
          "price": "25.88万",
          "fuelType": "插电式混合动力",
          "size": "4980x1862x1449",
          "manufacturer": "广汽本田",
          "class": "中型车",
          "power": "插电式混动 184马力"
        }
      ]
    },
    {
      "carName": "英仕派 PHEV",
      "mainImage": "https://p3.dcarimg.com/img/tos-cn-i-dcdx/0ad7bbb8e183443eb5acbfa3068ddcab~1200x0.png",
      "configs": [
        {
          "configName": "英仕派 PHEV 2025款 e:PHEV 智耀版",
          "price": "26.88万",
          "fuelType": "插电式混合动力",
          "size": "4979x1862x1449",
          "manufacturer": "东风本田",
          "class": "中型车",
          "power": "插电式混动 184马力"
        },
        {
          "configName": "英仕派 PHEV 2023款 e:PHEV 智尊版",
          "price": "22.98万",
          "fuelType": "插电式混合动力",
          "size": "4979x1862x1449",
          "manufacturer": "东风本田",
          "class": "中型车",
          "power": "插电式混动 184马力"
        },
        {
          "configName": "英仕派 PHEV 2023款 e:PHEV 智耀版",
          "price": "25.88万",
          "fuelType": "插电式混合动力",
          "size": "4979x1862x1449",
          "manufacturer": "东风本田",
          "class": "中型车",
          "power": "插电式混动 184马力"
        }
      ]
    },
    {
      "carName": "英仕派",
      "mainImage": "https://p3.dcarimg.com/img/tos-cn-i-dcdx/0bd0fa38d1c04455b58801d8b7e9a9c5~1200x0.png",
      "configs": [
        {
          "configName": "英仕派 2025款 260TURBO 典雅版",
          "price": "18.28万",
          "fuelType": "汽油",
          "size": "4979x1862x1449",
          "manufacturer": "东风本田",
          "class": "中型车",
          "power": "1.5T 192马力 L4"
        },
        {
          "configName": "英仕派 2025款 260TURBO 精英版",
          "price": "19.28万",
          "fuelType": "汽油",
          "size": "4979x1862x1449",
          "manufacturer": "东风本田",
          "class": "中型车",
          "power": "1.5T 192马力 L4"
        },
        {
          "configName": "英仕派 2025款 260TURBO 精逸版",
          "price": "21.38万",
          "fuelType": "汽油",
          "size": "4979x1862x1449",
          "manufacturer": "东风本田",
          "class": "中型车",
          "power": "1.5T 192马力 L4"
        },
        {
          "configName": "英仕派 2024款 260TURBO 精英版",
          "price": "19.28万",
          "fuelType": "汽油",
          "size": "4979x1862x1449",
          "manufacturer": "东风本田",
          "class": "中型车",
          "power": "1.5T 192马力 L4"
        },
        {
          "configName": "英仕派 2024款 260TURBO 精逸版",
          "price": "21.38万",
          "fuelType": "汽油",
          "size": "4979x1862x1449",
          "manufacturer": "东风本田",
          "class": "中型车",
          "power": "1.5T 192马力 L4"
        },
        {
          "configName": "英仕派 2023款 260TURBO 典雅版",
          "price": "18.28万",
          "fuelType": "汽油",
          "size": "4979x1862x1449",
          "manufacturer": "东风本田",
          "class": "中型车",
          "power": "1.5T 192马力 L4"
        },
        {
          "configName": "英仕派 2023款 260TURBO 精致版",
          "price": "19.18万",
          "fuelType": "汽油",
          "size": "4979x1862x1449",
          "manufacturer": "东风本田",
          "class": "中型车",
          "power": "1.5T 192马力 L4"
        },
        {
          "configName": "英仕派 2023款 260TURBO 精悦版",
          "price": "21.28万",
          "fuelType": "汽油",
          "size": "4979x1862x1449",
          "manufacturer": "东风本田",
          "class": "中型车",
          "power": "1.5T 192马力 L4"
        },
        {
          "configName": "英仕派 2023款 260TURBO 精耀版",
          "price": "22.98万",
          "fuelType": "汽油",
          "size": "4979x1862x1449",
          "manufacturer": "东风本田",
          "class": "中型车",
          "power": "1.5T 192马力 L4"
        }
      ]
    },
    {
      "carName": "东风本田S7",
      "mainImage": "https://p3.dcarimg.com/img/tos-cn-i-dcdx/94138d31d6964850bff16394205a4129~1200x0.png",
      "configs": [
        {
          "configName": "东风本田S7 2025款 650km 开拓者版",
          "price": "19.99万",
          "fuelType": "纯电动",
          "size": "4750x1930x1625",
          "manufacturer": "东风本田",
          "class": "中型SUV",
          "power": "纯电动 272马力"
        },
        {
          "configName": "东风本田S7 2025款 620km 领航者版",
          "price": "24.99万",
          "fuelType": "纯电动",
          "size": "4750x1930x1625",
          "manufacturer": "东风本田",
          "class": "中型SUV",
          "power": "纯电动 476马力"
        }
      ]
    },
    {
      "carName": "广汽本田P7",
      "mainImage": "https://p3.dcarimg.com/img/tos-cn-i-dcdx/57f624dec3e9421cbbbba02e7e095ec9~1200x0.png",
      "configs": [
        {
          "configName": "广汽本田P7 2025款 后驱长续航Pro",
          "price": "19.99万",
          "fuelType": "纯电动",
          "size": "4750x1930x1625",
          "manufacturer": "广汽本田",
          "class": "中型SUV",
          "power": "纯电动 272马力"
        },
        {
          "configName": "广汽本田P7 2025款 后驱长续航Plus",
          "price": "21.89万",
          "fuelType": "纯电动",
          "size": "4750x1930x1625",
          "manufacturer": "广汽本田",
          "class": "中型SUV",
          "power": "纯电动 272马力"
        },
        {
          "configName": "广汽本田P7 2025款 四驱长续航Max",
          "price": "24.99万",
          "fuelType": "纯电动",
          "size": "4750x1930x1625",
          "manufacturer": "广汽本田",
          "class": "中型SUV",
          "power": "纯电动 476马力"
        }
      ]
    },
    {
      "carName": "缤智",
      "mainImage": "https://p3.dcarimg.com/img/tos-cn-i-dcdx/a86066499bd542dba3bda68be9155d90~1200x0.png",
      "configs": [
        {
          "configName": "缤智 2025款 1.5L CVT舒享版",
          "price": "12.29万",
          "fuelType": "汽油",
          "size": "4380x1790x1590",
          "manufacturer": "广汽本田",
          "class": "小型SUV",
          "power": "1.5L 124马力 L4"
        },
        {
          "configName": "缤智 2023款 1.5L CVT精英版",
          "price": "11.99万",
          "fuelType": "汽油",
          "size": "4380x1790x1590",
          "manufacturer": "广汽本田",
          "class": "小型SUV",
          "power": "1.5L 124马力 L4"
        },
        {
          "configName": "缤智 2023款 1.5L CVT科技版",
          "price": "12.99万",
          "fuelType": "汽油",
          "size": "4380x1790x1590",
          "manufacturer": "广汽本田",
          "class": "小型SUV",
          "power": "1.5L 124马力 L4"
        },
        {
          "configName": "缤智 2023款 1.5L CVT先锋版",
          "price": "13.09万",
          "fuelType": "汽油",
          "size": "4380x1790x1590",
          "manufacturer": "广汽本田",
          "class": "小型SUV",
          "power": "1.5L 124马力 L4"
        },
        {
          "configName": "缤智 2023款 1.5L CVT豪华版",
          "price": "13.99万",
          "fuelType": "汽油",
          "size": "4380x1790x1590",
          "manufacturer": "广汽本田",
          "class": "小型SUV",
          "power": "1.5L 124马力 L4"
        }
      ]
    },
    {
      "carName": "XR-V",
      "mainImage": "https://p3.dcarimg.com/img/tos-cn-i-dcdx/1d7f858ce72f4870ab82c32961a47c3b~1200x0.png",
      "configs": [
        {
          "configName": "本田XR-V 2024款 1.5L CVT热力版",
          "price": "11.99万",
          "fuelType": "汽油",
          "size": "4380x1790x1590",
          "manufacturer": "东风本田",
          "class": "小型SUV",
          "power": "1.5L 124马力 L4"
        },
        {
          "configName": "本田XR-V 2024款 1.5L CVT热诚版",
          "price": "12.59万",
          "fuelType": "汽油",
          "size": "4380x1790x1590",
          "manufacturer": "东风本田",
          "class": "小型SUV",
          "power": "1.5L 124马力 L4"
        },
        {
          "configName": "本田XR-V 2024款 1.5L CVT热浪版",
          "price": "13.19万",
          "fuelType": "汽油",
          "size": "4380x1790x1590",
          "manufacturer": "东风本田",
          "class": "小型SUV",
          "power": "1.5L 124马力 L4"
        },
        {
          "configName": "本田XR-V 2024款 1.5L CVT热潮版",
          "price": "13.29万",
          "fuelType": "汽油",
          "size": "4380x1790x1590",
          "manufacturer": "东风本田",
          "class": "小型SUV",
          "power": "1.5L 124马力 L4"
        },
        {
          "configName": "本田XR-V 2024款 1.5L CVT热爱版",
          "price": "13.99万",
          "fuelType": "汽油",
          "size": "4380x1790x1590",
          "manufacturer": "东风本田",
          "class": "小型SUV",
          "power": "1.5L 124马力 L4"
        }
      ]
    },
    {
      "carName": "ZR-V 致在",
      "mainImage": "https://p3.dcarimg.com/img/tos-cn-i-dcdx/b5e8d5164fc946a09b2cf145ff2bd36e~1200x0.png",
      "configs": [
        {
          "configName": "ZR-V 致在 2023款 1.5T CVT科技版",
          "price": "16.49万",
          "fuelType": "汽油",
          "size": "4568x1840x1611",
          "manufacturer": "广汽本田",
          "class": "紧凑型SUV",
          "power": "1.5T 182马力 L4"
        },
        {
          "configName": "ZR-V 致在 2023款 2.0L 锐·精英版",
          "price": "17.99万",
          "fuelType": "油电混合",
          "size": "4568x1840x1611",
          "manufacturer": "广汽本田",
          "class": "紧凑型SUV",
          "power": "油电混合 184马力"
        },
        {
          "configName": "ZR-V 致在 2023款 1.5T CVT智享版",
          "price": "17.79万",
          "fuelType": "汽油",
          "size": "4568x1840x1621",
          "manufacturer": "广汽本田",
          "class": "紧凑型SUV",
          "power": "1.5T 182马力 L4"
        },
        {
          "configName": "ZR-V 致在 2023款 2.0L 锐·领先版",
          "price": "19.49万",
          "fuelType": "油电混合",
          "size": "4568x1840x1611",
          "manufacturer": "广汽本田",
          "class": "紧凑型SUV",
          "power": "油电混合 184马力"
        },
        {
          "configName": "ZR-V 致在 2023款 2.0L 锐·豪华版",
          "price": "20.69万",
          "fuelType": "油电混合",
          "size": "4568x1840x1621",
          "manufacturer": "广汽本田",
          "class": "紧凑型SUV",
          "power": "油电混合 184马力"
        },
        {
          "configName": "ZR-V 致在 2023款 2.0L 锐·尊享版",
          "price": "22.89万",
          "fuelType": "油电混合",
          "size": "4568x1840x1621",
          "manufacturer": "广汽本田",
          "class": "紧凑型SUV",
          "power": "油电混合 184马力"
        },
        {
          "configName": "ZR-V 致在 2022款 1.5T CVT精英版",
          "price": "15.99万",
          "fuelType": "汽油",
          "size": "4568x1840x1611",
          "manufacturer": "广汽本田",
          "class": "紧凑型SUV",
          "power": "1.5T 182马力 L4"
        },
        {
          "configName": "ZR-V 致在 2022款 1.5T CVT豪华版",
          "price": "17.89万",
          "fuelType": "汽油",
          "size": "4568x1840x1621",
          "manufacturer": "广汽本田",
          "class": "紧凑型SUV",
          "power": "1.5T 182马力 L4"
        },
        {
          "configName": "ZR-V 致在 2022款 1.5T CVT尊享版",
          "price": "19.59万",
          "fuelType": "汽油",
          "size": "4568x1840x1621",
          "manufacturer": "广汽本田",
          "class": "紧凑型SUV",
          "power": "1.5T 182马力 L4"
        }
      ]
    },
    {
      "carName": "e:NS1",
      "mainImage": "https://p3.dcarimg.com/img/motor-mis-img/5bbc1fd1fc8eb64258ca124040493af0~1200x0.png",
      "configs": [
        {
          "configName": "本田e:NS1 2022款 e型版",
          "price": "17.5万",
          "fuelType": "纯电动",
          "size": "4390x1790x1560",
          "manufacturer": "东风本田",
          "class": "小型SUV",
          "power": "纯电动 182马力"
        },
        {
          "configName": "本田e:NS1 2022款 e驰版",
          "price": "18.9万",
          "fuelType": "纯电动",
          "size": "4390x1790x1560",
          "manufacturer": "东风本田",
          "class": "小型SUV",
          "power": "纯电动 182马力"
        },
        {
          "configName": "本田e:NS1 2022款 e动版",
          "price": "20.7万",
          "fuelType": "纯电动",
          "size": "4390x1790x1560",
          "manufacturer": "东风本田",
          "class": "小型SUV",
          "power": "纯电动 204马力"
        },
        {
          "configName": "本田e:NS1 2022款 e境版",
          "price": "21.8万",
          "fuelType": "纯电动",
          "size": "4390x1790x1560",
          "manufacturer": "东风本田",
          "class": "小型SUV",
          "power": "纯电动 204马力"
        }
      ]
    },
    {
      "carName": "e:NP1 极湃1",
      "mainImage": "https://p3.dcarimg.com/img/tos-cn-i-dcdx/debb281d003e4d3eb6e9339eb4ff9100~1200x0.png",
      "configs": [
        {
          "configName": "e:NP1 极湃1 2023款 420km 见极版",
          "price": "17.5万",
          "fuelType": "纯电动",
          "size": "4388x1790x1560",
          "manufacturer": "广汽本田",
          "class": "小型SUV",
          "power": "纯电动 182马力"
        },
        {
          "configName": "e:NP1 极湃1 2023款 420km 进极版",
          "price": "18.9万",
          "fuelType": "纯电动",
          "size": "4388x1790x1560",
          "manufacturer": "广汽本田",
          "class": "小型SUV",
          "power": "纯电动 182马力"
        },
        {
          "configName": "e:NP1 极湃1 2023款 510km 览极版",
          "price": "20.5万",
          "fuelType": "纯电动",
          "size": "4388x1790x1560",
          "manufacturer": "广汽本田",
          "class": "小型SUV",
          "power": "纯电动 204马力"
        },
        {
          "configName": "e:NP1 极湃1 2023款 510km 绽极版",
          "price": "21.8万",
          "fuelType": "纯电动",
          "size": "4388x1790x1560",
          "manufacturer": "广汽本田",
          "class": "小型SUV",
          "power": "纯电动 204马力"
        }
      ]
    },
    {
      "carName": "HR-V",
      "mainImage": "https://p3.dcarimg.com/img/tos-cn-i-dcdx/36f937e6715d4a57b574d24353ce5272~1200x0.png",
      "configs": [
        {
          "configName": "本田HR-V 2024款 240TURBO CVT劲悦版",
          "price": "17.59万",
          "fuelType": "汽油",
          "size": "4569x1840x1621",
          "manufacturer": "东风本田",
          "class": "紧凑型SUV",
          "power": "1.5T 182马力 L4"
        },
        {
          "configName": "本田HR-V 2023款 240TURBO CVT劲享版",
          "price": "15.99万",
          "fuelType": "汽油",
          "size": "4569x1840x1611",
          "manufacturer": "东风本田",
          "class": "紧凑型SUV",
          "power": "1.5T 182马力 L4"
        },
        {
          "configName": "本田HR-V 2023款 240TURBO CVT劲睿版",
          "price": "16.29万",
          "fuelType": "汽油",
          "size": "4569x1840x1611",
          "manufacturer": "东风本田",
          "class": "紧凑型SUV",
          "power": "1.5T 182马力 L4"
        },
        {
          "configName": "本田HR-V 2023款 240TURBO CVT劲潮版",
          "price": "17.49万",
          "fuelType": "汽油",
          "size": "4569x1840x1621",
          "manufacturer": "东风本田",
          "class": "紧凑型SUV",
          "power": "1.5T 182马力 L4"
        },
        {
          "configName": "本田HR-V 2023款 240TURBO CVT劲致版",
          "price": "19.59万",
          "fuelType": "汽油",
          "size": "4569x1840x1621",
          "manufacturer": "东风本田",
          "class": "紧凑型SUV",
          "power": "1.5T 182马力 L4"
        },
        {
          "configName": "本田HR-V 2023款 2.0L e:HEV 动速版",
          "price": "17.99万",
          "fuelType": "油电混合",
          "size": "4569x1840x1611",
          "manufacturer": "东风本田",
          "class": "紧凑型SUV",
          "power": "油电混合 184马力"
        },
        {
          "configName": "本田HR-V 2023款 2.0L e:HEV 动智版",
          "price": "19.09万",
          "fuelType": "油电混合",
          "size": "4569x1840x1611",
          "manufacturer": "东风本田",
          "class": "紧凑型SUV",
          "power": "油电混合 184马力"
        },
        {
          "configName": "本田HR-V 2023款 2.0L e:HEV 动擎版",
          "price": "20.59万",
          "fuelType": "油电混合",
          "size": "4569x1840x1621",
          "manufacturer": "东风本田",
          "class": "紧凑型SUV",
          "power": "油电混合 184马力"
        },
        {
          "configName": "本田HR-V 2023款 2.0L e:HEV 动魄版",
          "price": "22.89万",
          "fuelType": "油电混合",
          "size": "4569x1840x1621",
          "manufacturer": "东风本田",
          "class": "紧凑型SUV",
          "power": "油电混合 184马力"
        }
      ]
    },
    {
      "carName": "CR-V PHEV",
      "mainImage": "https://p3.dcarimg.com/img/tos-cn-i-dcdx/0917aff9b27f44eca5d35cd2e56e4483~1200x0.png",
      "configs": [
        {
          "configName": "本田CR-V PHEV 2023款 e:PHEV 2.0L 领创版",
          "price": "22.59万",
          "fuelType": "插电式混合动力",
          "size": "4703x1866x1680",
          "manufacturer": "东风本田",
          "class": "紧凑型SUV",
          "power": "插电式混动 184马力"
        },
        {
          "configName": "本田CR-V PHEV 2023款 e:PHEV 2.0L 领越版",
          "price": "24.99万",
          "fuelType": "插电式混合动力",
          "size": "4703x1866x1680",
          "manufacturer": "东风本田",
          "class": "紧凑型SUV",
          "power": "插电式混动 184马力"
        },
        {
          "configName": "本田CR-V PHEV 2023款 e:PHEV 2.0L 领耀版",
          "price": "26.99万",
          "fuelType": "插电式混合动力",
          "size": "4703x1866x1680",
          "manufacturer": "东风本田",
          "class": "紧凑型SUV",
          "power": "插电式混动 184马力"
        }
      ]
    },
    {
      "carName": "猎光e:NS2",
      "mainImage": "https://p3.dcarimg.com/img/tos-cn-i-dcdx/7b885632825143e68caefbae5a64d4bd~1200x0.png",
      "configs": [
        {
          "configName": "猎光e:NS2 2024款 锐光版",
          "price": "18.98万",
          "fuelType": "纯电动",
          "size": "4788x1838x1570",
          "manufacturer": "东风本田",
          "class": "紧凑型SUV",
          "power": "纯电动 204马力"
        },
        {
          "configName": "猎光e:NS2 2024款 炫光版",
          "price": "19.98万",
          "fuelType": "纯电动",
          "size": "4788x1838x1570",
          "manufacturer": "东风本田",
          "class": "紧凑型SUV",
          "power": "纯电动 204马力"
        },
        {
          "configName": "猎光e:NS2 2024款 熠光版",
          "price": "19.98万",
          "fuelType": "纯电动",
          "size": "4788x1838x1570",
          "manufacturer": "东风本田",
          "class": "紧凑型SUV",
          "power": "纯电动 204马力"
        },
        {
          "configName": "猎光e:NS2 2024款 驭光版",
          "price": "20.98万",
          "fuelType": "纯电动",
          "size": "4788x1838x1570",
          "manufacturer": "东风本田",
          "class": "紧凑型SUV",
          "power": "纯电动 204马力"
        }
      ]
    },
    {
      "carName": "CR-V",
      "mainImage": "https://p3.dcarimg.com/img/tos-cn-i-dcdx/507a4c032d564fb7badbb82f893a977c~1200x0.png",
      "configs": [
        {
          "configName": "本田CR-V 2024款 240TURBO CVT两驱活力5座版",
          "price": "18.59万",
          "fuelType": "汽油",
          "size": "4703x1866x1680",
          "manufacturer": "东风本田",
          "class": "紧凑型SUV",
          "power": "1.5T 193马力 L4"
        },
        {
          "configName": "本田CR-V 2024款 240TURBO CVT两驱锋尚5座版",
          "price": "20.19万",
          "fuelType": "汽油",
          "size": "4703x1866x1680",
          "manufacturer": "东风本田",
          "class": "紧凑型SUV",
          "power": "1.5T 193马力 L4"
        },
        {
          "configName": "本田CR-V 2024款 240TURBO CVT两驱锋尚7座版",
          "price": "20.89万",
          "fuelType": "汽油",
          "size": "4703x1866x1680",
          "manufacturer": "东风本田",
          "class": "紧凑型SUV",
          "power": "1.5T 193马力 L4"
        },
        {
          "configName": "本田CR-V 2024款 240TURBO CVT两驱智领5座版",
          "price": "21.19万",
          "fuelType": "汽油",
          "size": "4703x1866x1680",
          "manufacturer": "东风本田",
          "class": "紧凑型SUV",
          "power": "1.5T 193马力 L4"
        },
        {
          "configName": "本田CR-V 2024款 240TURBO CVT两驱臻享7座版",
          "price": "23.19万",
          "fuelType": "汽油",
          "size": "4703x1866x1680",
          "manufacturer": "东风本田",
          "class": "紧凑型SUV",
          "power": "1.5T 193马力 L4"
        },
        {
          "configName": "本田CR-V 2024款 240TURBO CVT四驱臻享5座版",
          "price": "23.19万",
          "fuelType": "汽油",
          "size": "4703x1866x1690",
          "manufacturer": "东风本田",
          "class": "紧凑型SUV",
          "power": "1.5T 193马力 L4"
        },
        {
          "configName": "本田CR-V 2024款 240TURBO CVT四驱尊耀5座版",
          "price": "24.99万",
          "fuelType": "汽油",
          "size": "4703x1866x1690",
          "manufacturer": "东风本田",
          "class": "紧凑型SUV",
          "power": "1.5T 193马力 L4"
        },
        {
          "configName": "本田CR-V 2024款 e:HEV 2.0L 两驱智逸版",
          "price": "21.99万",
          "fuelType": "油电混合",
          "size": "4703x1866x1680",
          "manufacturer": "东风本田",
          "class": "紧凑型SUV",
          "power": "油电混合 184马力"
        },
        {
          "configName": "本田CR-V 2024款 e:HEV 2.0L 两驱智睿版",
          "price": "23.49万",
          "fuelType": "油电混合",
          "size": "4703x1866x1680",
          "manufacturer": "东风本田",
          "class": "紧凑型SUV",
          "power": "油电混合 184马力"
        },
        {
          "configName": "本田CR-V 2023款 240TURBO CVT两驱活力5座版",
          "price": "18.59万",
          "fuelType": "汽油",
          "size": "4703x1866x1680",
          "manufacturer": "东风本田",
          "class": "紧凑型SUV",
          "power": "1.5T 193马力 L4"
        },
        {
          "configName": "本田CR-V 2023款 240TURBO CVT两驱锋尚5座版",
          "price": "20.19万",
          "fuelType": "汽油",
          "size": "4703x1866x1680",
          "manufacturer": "东风本田",
          "class": "紧凑型SUV",
          "power": "1.5T 193马力 L4"
        },
        {
          "configName": "本田CR-V 2023款 240TURBO CVT两驱锋尚7座版",
          "price": "20.89万",
          "fuelType": "汽油",
          "size": "4703x1866x1680",
          "manufacturer": "东风本田",
          "class": "紧凑型SUV",
          "power": "1.5T 193马力 L4"
        },
        {
          "configName": "本田CR-V 2023款 240TURBO CVT两驱睿型5座版",
          "price": "21.09万",
          "fuelType": "汽油",
          "size": "4703x1866x1680",
          "manufacturer": "东风本田",
          "class": "紧凑型SUV",
          "power": "1.5T 193马力 L4"
        },
        {
          "configName": "本田CR-V 2023款 240TURBO CVT两驱智领5座版",
          "price": "21.19万",
          "fuelType": "汽油",
          "size": "4703x1866x1680",
          "manufacturer": "东风本田",
          "class": "紧凑型SUV",
          "power": "1.5T 193马力 L4"
        },
        {
          "configName": "本田CR-V 2023款 240TURBO CVT两驱臻享7座版",
          "price": "23.19万",
          "fuelType": "汽油",
          "size": "4703x1866x1680",
          "manufacturer": "东风本田",
          "class": "紧凑型SUV",
          "power": "1.5T 193马力 L4"
        },
        {
          "configName": "本田CR-V 2023款 240TURBO CVT四驱臻享5座版",
          "price": "23.19万",
          "fuelType": "汽油",
          "size": "4703x1866x1690",
          "manufacturer": "东风本田",
          "class": "紧凑型SUV",
          "power": "1.5T 193马力 L4"
        },
        {
          "configName": "本田CR-V 2023款 240TURBO CVT四驱尊耀5座版",
          "price": "24.99万",
          "fuelType": "汽油",
          "size": "4703x1866x1690",
          "manufacturer": "东风本田",
          "class": "紧凑型SUV",
          "power": "1.5T 193马力 L4"
        },
        {
          "configName": "本田CR-V 2023款 e:HEV 2.0L 两驱智尚版",
          "price": "19.99万",
          "fuelType": "油电混合",
          "size": "4703x1866x1680",
          "manufacturer": "东风本田",
          "class": "紧凑型SUV",
          "power": "油电混合 184马力"
        },
        {
          "configName": "本田CR-V 2023款 e:HEV 2.0L 两驱智享版",
          "price": "20.99万",
          "fuelType": "油电混合",
          "size": "4703x1866x1680",
          "manufacturer": "东风本田",
          "class": "紧凑型SUV",
          "power": "油电混合 184马力"
        },
        {
          "configName": "本田CR-V 2023款 e:HEV 2.0L 两驱智悦版",
          "price": "21.99万",
          "fuelType": "油电混合",
          "size": "4703x1866x1680",
          "manufacturer": "东风本田",
          "class": "紧凑型SUV",
          "power": "油电混合 184马力"
        },
        {
          "configName": "本田CR-V 2023款 e:HEV 2.0L 两驱智耀版",
          "price": "23.39万",
          "fuelType": "油电混合",
          "size": "4703x1866x1680",
          "manufacturer": "东风本田",
          "class": "紧凑型SUV",
          "power": "油电混合 184马力"
        },
        {
          "configName": "本田CR-V 2023款 e:HEV 2.0L 四驱智尊版",
          "price": "26.39万",
          "fuelType": "油电混合",
          "size": "4703x1866x1690",
          "manufacturer": "东风本田",
          "class": "紧凑型SUV",
          "power": "油电混合 184马力"
        }
      ]
    },
    {
      "carName": "皓影",
      "mainImage": "https://p3.dcarimg.com/img/tos-cn-i-dcdx/88c65697ba3f4019bbff39e38e3d614c~1200x0.png",
      "configs": [
        {
          "configName": "皓影 2025款 240TURBO CVT两驱精英版",
          "price": "18.59万",
          "fuelType": "汽油",
          "size": "4716x1866x1681",
          "manufacturer": "广汽本田",
          "class": "紧凑型SUV",
          "power": "1.5T 193马力 L4"
        },
        {
          "configName": "皓影 2025款 240TURBO CVT两驱豪华版",
          "price": "19.99万",
          "fuelType": "汽油",
          "size": "4716x1866x1681",
          "manufacturer": "广汽本田",
          "class": "紧凑型SUV",
          "power": "1.5T 193马力 L4"
        },
        {
          "configName": "皓影 2025款 240TURBO CVT两驱尊贵版",
          "price": "21.39万",
          "fuelType": "汽油",
          "size": "4716x1866x1681",
          "manufacturer": "广汽本田",
          "class": "紧凑型SUV",
          "power": "1.5T 193马力 L4"
        },
        {
          "configName": "皓影 2025款 240TURBO CVT四驱尊享版",
          "price": "24.99万",
          "fuelType": "汽油",
          "size": "4716x1866x1691",
          "manufacturer": "广汽本田",
          "class": "紧凑型SUV",
          "power": "1.5T 193马力 L4"
        },
        {
          "configName": "皓影 2025款 锐·混动 2.0L 两驱豪华版",
          "price": "19.99万",
          "fuelType": "油电混合",
          "size": "4716x1866x1681",
          "manufacturer": "广汽本田",
          "class": "紧凑型SUV",
          "power": "油电混动 184马力"
        },
        {
          "configName": "皓影 2025款 锐·混动 2.0L 两驱尊耀版",
          "price": "21.99万",
          "fuelType": "油电混合",
          "size": "4716x1866x1681",
          "manufacturer": "广汽本田",
          "class": "紧凑型SUV",
          "power": "油电混动 184马力"
        },
        {
          "configName": "皓影 2025款 锐·混动 2.0L 四驱尊耀版",
          "price": "23.29万",
          "fuelType": "油电混合",
          "size": "4716x1866x1691",
          "manufacturer": "广汽本田",
          "class": "紧凑型SUV",
          "power": "油电混动 184马力"
        },
        {
          "configName": "皓影 2025款 锐·混动 2.0L 两驱尊享版",
          "price": "23.49万",
          "fuelType": "油电混合",
          "size": "4716x1866x1681",
          "manufacturer": "广汽本田",
          "class": "紧凑型SUV",
          "power": "油电混动 184马力"
        },
        {
          "configName": "皓影 2025款 锐·混动 2.0L 四驱至尊版",
          "price": "26.39万",
          "fuelType": "油电混合",
          "size": "4716x1866x1691",
          "manufacturer": "广汽本田",
          "class": "紧凑型SUV",
          "power": "油电混动 184马力"
        },
        {
          "configName": "皓影 2024款 锐·混动 2.0L 两驱尊耀版",
          "price": "21.99万",
          "fuelType": "油电混合",
          "size": "4716x1866x1681",
          "manufacturer": "广汽本田",
          "class": "紧凑型SUV",
          "power": "油电混动 184马力"
        },
        {
          "configName": "皓影 2024款 锐·混动 2.0L 四驱尊耀版",
          "price": "23.29万",
          "fuelType": "油电混合",
          "size": "4716x1866x1691",
          "manufacturer": "广汽本田",
          "class": "紧凑型SUV",
          "power": "油电混动 184马力"
        },
        {
          "configName": "皓影 2023款 240TURBO CVT两驱精英版",
          "price": "18.59万",
          "fuelType": "汽油",
          "size": "4716x1866x1681",
          "manufacturer": "广汽本田",
          "class": "紧凑型SUV",
          "power": "1.5T 193马力 L4"
        },
        {
          "configName": "皓影 2023款 240TURBO CVT两驱精英版PRO",
          "price": "19.59万",
          "fuelType": "汽油",
          "size": "4716x1866x1681",
          "manufacturer": "广汽本田",
          "class": "紧凑型SUV",
          "power": "1.5T 193马力 L4"
        },
        {
          "configName": "皓影 2023款 240TURBO CVT两驱豪华版",
          "price": "19.99万",
          "fuelType": "汽油",
          "size": "4716x1866x1681",
          "manufacturer": "广汽本田",
          "class": "紧凑型SUV",
          "power": "1.5T 193马力 L4"
        },
        {
          "configName": "皓影 2023款 240TURBO CVT两驱豪华版PRO",
          "price": "20.49万",
          "fuelType": "汽油",
          "size": "4716x1866x1681",
          "manufacturer": "广汽本田",
          "class": "紧凑型SUV",
          "power": "1.5T 193马力 L4"
        },
        {
          "configName": "皓影 2023款 240TURBO CVT两驱尊耀版",
          "price": "21.29万",
          "fuelType": "汽油",
          "size": "4716x1866x1681",
          "manufacturer": "广汽本田",
          "class": "紧凑型SUV",
          "power": "1.5T 193马力 L4"
        },
        {
          "configName": "皓影 2023款 240TURBO CVT两驱尊贵版",
          "price": "21.39万",
          "fuelType": "汽油",
          "size": "4716x1866x1681",
          "manufacturer": "广汽本田",
          "class": "紧凑型SUV",
          "power": "1.5T 193马力 L4"
        },
        {
          "configName": "皓影 2023款 240TURBO CVT两驱尊贵版PRO",
          "price": "22.99万",
          "fuelType": "汽油",
          "size": "4716x1866x1681",
          "manufacturer": "广汽本田",
          "class": "紧凑型SUV",
          "power": "1.5T 193马力 L4"
        },
        {
          "configName": "皓影 2023款 240TURBO CVT四驱尊享版",
          "price": "24.99万",
          "fuelType": "汽油",
          "size": "4716x1866x1691",
          "manufacturer": "广汽本田",
          "class": "紧凑型SUV",
          "power": "1.5T 193马力 L4"
        },
        {
          "configName": "皓影 2023款 锐·混动 2.0L 两驱豪华版",
          "price": "19.99万",
          "fuelType": "油电混合",
          "size": "4716x1866x1681",
          "manufacturer": "广汽本田",
          "class": "紧凑型SUV",
          "power": "油电混动 184马力"
        },
        {
          "configName": "皓影 2023款 锐·混动 2.0L 两驱尊贵版",
          "price": "21.99万",
          "fuelType": "油电混合",
          "size": "4716x1866x1681",
          "manufacturer": "广汽本田",
          "class": "紧凑型SUV",
          "power": "油电混动 184马力"
        },
        {
          "configName": "皓影 2023款 锐·混动 2.0L 两驱尊享版",
          "price": "23.49万",
          "fuelType": "油电混合",
          "size": "4716x1866x1681",
          "manufacturer": "广汽本田",
          "class": "紧凑型SUV",
          "power": "油电混动 184马力"
        },
        {
          "configName": "皓影 2023款 锐·混动 2.0L 四驱尊贵版",
          "price": "23.19万",
          "fuelType": "油电混合",
          "size": "4716x1866x1691",
          "manufacturer": "广汽本田",
          "class": "紧凑型SUV",
          "power": "油电混动 184马力"
        },
        {
          "configName": "皓影 2023款 锐·混动 2.0L 四驱至尊版",
          "price": "26.39万",
          "fuelType": "油电混合",
          "size": "4716x1866x1691",
          "manufacturer": "广汽本田",
          "class": "紧凑型SUV",
          "power": "油电混动 184马力"
        }
      ]
    },
    {
      "carName": "皓影 PHEV",
      "mainImage": "https://p3.dcarimg.com/img/tos-cn-i-dcdx/bdfcb8a134d14249ab8146911a92cebf~1200x0.png",
      "configs": [
        {
          "configName": "皓影 PHEV 2025款 e:PHEV 尊贵版",
          "price": "22.59万",
          "fuelType": "插电式混合动力",
          "size": "4716x1866x1681",
          "manufacturer": "广汽本田",
          "class": "紧凑型SUV",
          "power": "插电式混动 184马力"
        },
        {
          "configName": "皓影 PHEV 2025款 e:PHEV 尊享版",
          "price": "24.89万",
          "fuelType": "插电式混合动力",
          "size": "4716x1866x1681",
          "manufacturer": "广汽本田",
          "class": "紧凑型SUV",
          "power": "插电式混动 184马力"
        },
        {
          "configName": "皓影 PHEV 2025款 e:PHEV 至尊版",
          "price": "26.99万",
          "fuelType": "插电式混合动力",
          "size": "4716x1866x1681",
          "manufacturer": "广汽本田",
          "class": "紧凑型SUV",
          "power": "插电式混动 184马力"
        },
        {
          "configName": "皓影 PHEV 2023款 e:PHEV 尊贵版",
          "price": "22.59万",
          "fuelType": "插电式混合动力",
          "size": "4716x1866x1681",
          "manufacturer": "广汽本田",
          "class": "紧凑型SUV",
          "power": "插电式混动 184马力"
        },
        {
          "configName": "皓影 PHEV 2023款 e:PHEV 尊享版",
          "price": "24.89万",
          "fuelType": "插电式混合动力",
          "size": "4716x1866x1681",
          "manufacturer": "广汽本田",
          "class": "紧凑型SUV",
          "power": "插电式混动 184马力"
        },
        {
          "configName": "皓影 PHEV 2023款 e:PHEV 至尊版",
          "price": "26.99万",
          "fuelType": "插电式混合动力",
          "size": "4716x1866x1681",
          "manufacturer": "广汽本田",
          "class": "紧凑型SUV",
          "power": "插电式混动 184马力"
        }
      ]
    },
    {
      "carName": "冠道",
      "mainImage": "https://p3.dcarimg.com/img/tos-cn-i-dcdx/e21f5b579f3146e78d4f5c88e864d432~1200x0.png",
      "configs": [
        {
          "configName": "冠道 2023款 240 TURBO CVT 舒享版",
          "price": "23.98万",
          "fuelType": "汽油",
          "size": "4858x1942x1670",
          "manufacturer": "广汽本田",
          "class": "中型SUV",
          "power": "1.5T 188马力 L4"
        },
        {
          "configName": "冠道 2023款 240 TURBO CVT 智享版",
          "price": "25.58万",
          "fuelType": "汽油",
          "size": "4858x1942x1670",
          "manufacturer": "广汽本田",
          "class": "中型SUV",
          "power": "1.5T 188马力 L4"
        },
        {
          "configName": "冠道 2023款 240 TURBO CVT 幻夜尊享版",
          "price": "26.88万",
          "fuelType": "汽油",
          "size": "4858x1942x1670",
          "manufacturer": "广汽本田",
          "class": "中型SUV",
          "power": "1.5T 188马力 L4"
        },
        {
          "configName": "冠道 2023款 370 TURBO 9AT 豪华版",
          "price": "27.98万",
          "fuelType": "汽油",
          "size": "4858x1942x1670",
          "manufacturer": "广汽本田",
          "class": "中型SUV",
          "power": "2.0T 261马力 L4"
        },
        {
          "configName": "冠道 2023款 370 TURBO 9AT 尊享版 AWD",
          "price": "29.28万",
          "fuelType": "汽油",
          "size": "4858x1942x1675",
          "manufacturer": "广汽本田",
          "class": "中型SUV",
          "power": "2.0T 261马力 L4"
        },
        {
          "configName": "冠道 2023款 370 TURBO 9AT 幻夜尊享版 AWD",
          "price": "29.58万",
          "fuelType": "汽油",
          "size": "4858x1942x1675",
          "manufacturer": "广汽本田",
          "class": "中型SUV",
          "power": "2.0T 261马力 L4"
        },
        {
          "configName": "冠道 2023款 370 TURBO 9AT 至尊版 AWD 双色",
          "price": "32.98万",
          "fuelType": "汽油",
          "size": "4858x1942x1675",
          "manufacturer": "广汽本田",
          "class": "中型SUV",
          "power": "2.0T 261马力 L4"
        },
        {
          "configName": "冠道 2023款 370 TURBO 9AT 幻夜至尊版 AWD",
          "price": "32.98万",
          "fuelType": "汽油",
          "size": "4858x1942x1675",
          "manufacturer": "广汽本田",
          "class": "中型SUV",
          "power": "2.0T 261马力 L4"
        }
      ]
    },
    {
      "carName": "UR-V",
      "mainImage": "https://p3.dcarimg.com/img/tos-cn-i-dcdx/3ea48af1626443d09b7b81cb1939145f~1200x0.png",
      "configs": [
        {
          "configName": "本田UR-V 2024款 240TURBO 两驱致悦版",
          "price": "24.68万",
          "fuelType": "汽油",
          "size": "4856x1942x1670",
          "manufacturer": "东风本田",
          "class": "中型SUV",
          "power": "1.5T 188马力 L4"
        },
        {
          "configName": "本田UR-V 2024款 240TURBO 两驱致境版",
          "price": "25.68万",
          "fuelType": "汽油",
          "size": "4856x1942x1670",
          "manufacturer": "东风本田",
          "class": "中型SUV",
          "power": "1.5T 188马力 L4"
        },
        {
          "configName": "本田UR-V 2024款 240TURBO 两驱致雅版",
          "price": "26.88万",
          "fuelType": "汽油",
          "size": "4856x1942x1670",
          "manufacturer": "东风本田",
          "class": "中型SUV",
          "power": "1.5T 188马力 L4"
        },
        {
          "configName": "本田UR-V 2024款 240TURBO 两驱致雅黑爵士版",
          "price": "27.18万",
          "fuelType": "汽油",
          "size": "4856x1942x1670",
          "manufacturer": "东风本田",
          "class": "中型SUV",
          "power": "1.5T 188马力 L4"
        },
        {
          "configName": "本田UR-V 2024款 370TURBO 两驱尊雅版",
          "price": "27.98万",
          "fuelType": "汽油",
          "size": "4856x1942x1670",
          "manufacturer": "东风本田",
          "class": "中型SUV",
          "power": "2.0T 261马力 L4"
        },
        {
          "configName": "本田UR-V 2024款 370TURBO 四驱尊享版",
          "price": "29.38万",
          "fuelType": "汽油",
          "size": "4856x1942x1675",
          "manufacturer": "东风本田",
          "class": "中型SUV",
          "power": "2.0T 261马力 L4"
        },
        {
          "configName": "本田UR-V 2024款 370TURBO 四驱尊耀版",
          "price": "32.68万",
          "fuelType": "汽油",
          "size": "4856x1942x1675",
          "manufacturer": "东风本田",
          "class": "中型SUV",
          "power": "2.0T 261马力 L4"
        },
        {
          "configName": "本田UR-V 2024款 370TURBO 四驱尊耀黑爵士版",
          "price": "32.98万",
          "fuelType": "汽油",
          "size": "4856x1942x1675",
          "manufacturer": "东风本田",
          "class": "中型SUV",
          "power": "2.0T 261马力 L4"
        }
      ]
    },
    {
      "carName": "艾力绅",
      "mainImage": "https://p3.dcarimg.com/img/tos-cn-i-dcdx/a3e2f106e07b44c9af4628c826066f7c~1200x0.png",
      "configs": [
        {
          "configName": "艾力绅 2024款 2.0L e:HEV经典版",
          "price": "27.98万",
          "fuelType": "油电混合",
          "size": "4951x1842x1711",
          "manufacturer": "东风本田",
          "class": "中型MPV",
          "power": "油电混合 184马力"
        },
        {
          "configName": "艾力绅 2024款 2.0L e:HEV舒适版",
          "price": "29.88万",
          "fuelType": "油电混合",
          "size": "4951x1842x1711",
          "manufacturer": "东风本田",
          "class": "中型MPV",
          "power": "油电混合 184马力"
        },
        {
          "configName": "艾力绅 2024款 2.0L e:HEV豪华版",
          "price": "31.08万",
          "fuelType": "油电混合",
          "size": "4951x1842x1711",
          "manufacturer": "东风本田",
          "class": "中型MPV",
          "power": "油电混合 184马力"
        },
        {
          "configName": "艾力绅 2024款 2.0L e:HEV至尊版",
          "price": "33.18万",
          "fuelType": "油电混合",
          "size": "4951x1842x1711",
          "manufacturer": "东风本田",
          "class": "中型MPV",
          "power": "油电混合 184马力"
        }
      ]
    }
  ]
}