{
  "brand": "红旗",
  "brandImage": "https://p1-dcd.byteimg.com/img/motor-mis-img/9a2cf4552de5fd67f7f3a1f241ed9b48~tplv-resize:100:100.image",
  "cars": [
    {
      "carName": "红旗天工05",
      "mainImage": "https://p3.dcarimg.com/img/tos-cn-i-dcdx/620fd5005f62415c8d711bf65b4c458b~1200x0.png",
      "seriesName": "一汽红旗/中型车",
      "configs": [
        {
          "configName": "红旗天工05 2025款 550版",
          "price": "15.98万",
          "fuelType": "纯电动",
          "size": "4820x1915x1480"
        },
        {
          "configName": "红旗天工05 2025款 550 智选版",
          "price": "16.98万",
          "fuelType": "纯电动",
          "size": "4820x1915x1480"
        },
        {
          "configName": "红旗天工05 2025款 750版",
          "price": "17.58万",
          "fuelType": "纯电动",
          "size": "4820x1915x1480"
        },
        {
          "configName": "红旗天工05 2025款 750 智选版",
          "price": "18.58万",
          "fuelType": "纯电动",
          "size": "4820x1915x1480"
        }
      ]
    },
    {
      "carName": "红旗H5",
      "mainImage": "https://p3.dcarimg.com/img/tos-cn-i-dcdx/223bdb543bde49d5b683871a9b80c281~1200x0.png",
      "seriesName": "一汽红旗/中型车",
      "configs": [
        {
          "configName": "红旗H5 2025款 1.5T DCT旗悦50万辆纪念版",
          "price": "15.98万",
          "fuelType": "汽油",
          "size": "4988x1875x1470"
        },
        {
          "configName": "红旗H5 2025款 1.5T DCT旗韵50万辆纪念版",
          "price": "16.98万",
          "fuelType": "汽油",
          "size": "4988x1875x1470"
        },
        {
          "configName": "红旗H5 2025款 1.5T DCT玄影版",
          "price": "17.28万",
          "fuelType": "汽油",
          "size": "4988x1875x1470"
        },
        {
          "configName": "红旗H5 2025款 1.5T DCT60万辆纪念版",
          "price": "17.58万",
          "fuelType": "汽油",
          "size": "4988x1875x1470"
        },
        {
          "configName": "红旗H5 2025款 2.0T 自动旗享50万辆纪念版",
          "price": "17.98万",
          "fuelType": "汽油",
          "size": "4988x1875x1470"
        },
        {
          "configName": "红旗H5 2025款 2.0T 自动旗畅50万辆纪念版",
          "price": "18.98万",
          "fuelType": "汽油",
          "size": "4988x1875x1470"
        },
        {
          "configName": "红旗H5 2025款 2.0T 自动玄影版",
          "price": "19.28万",
          "fuelType": "汽油",
          "size": "4988x1875x1470"
        },
        {
          "configName": "红旗H5 2025款 2.0T 自动旗领50万辆纪念版",
          "price": "21.58万",
          "fuelType": "汽油",
          "size": "4988x1875x1470"
        },
        {
          "configName": "红旗H5 2025款 1.5T HEV 旗韵50万辆纪念版",
          "price": "18.98万",
          "fuelType": "油电混合",
          "size": "4988x1875x1470"
        },
        {
          "configName": "红旗H5 2025款 1.5T HEV 旗畅50万辆纪念版",
          "price": "19.98万",
          "fuelType": "油电混合",
          "size": "4988x1875x1470"
        },
        {
          "configName": "红旗H5 2025款 1.5T HEV 旗领50万辆纪念版",
          "price": "22.58万",
          "fuelType": "油电混合",
          "size": "4988x1875x1470"
        }
      ]
    },
    {
      "carName": "红旗H5 PHEV",
      "mainImage": "https://p3.dcarimg.com/img/tos-cn-i-dcdx/6033cb1b8b2d47b89f338be86aea4838~1200x0.png",
      "seriesName": "一汽红旗/中型车",
      "configs": [
        {
          "configName": "红旗H5 PHEV 2025款 130 超混版",
          "price": "18.58万",
          "fuelType": "插电式混合动力",
          "size": "4988x1875x1500"
        },
        {
          "configName": "红旗H5 PHEV 2025款 170 超混版",
          "price": "19.98万",
          "fuelType": "插电式混合动力",
          "size": "4988x1875x1500"
        }
      ]
    },
    {
      "carName": "红旗H6",
      "mainImage": "https://p3.dcarimg.com/img/tos-cn-i-dcdx/96c26c4143cf4975a0efa150f17f0993~1200x0.png",
      "seriesName": "一汽红旗/中型车",
      "configs": [
        {
          "configName": "红旗H6 2025款 2.0T 致行版",
          "price": "17.98万",
          "fuelType": "汽油",
          "size": "4990x1880x1455"
        },
        {
          "configName": "红旗H6 2025款 2.0T 致美版",
          "price": "19.28万",
          "fuelType": "汽油",
          "size": "4990x1880x1455"
        },
        {
          "configName": "红旗H6 2025款 2.0T 致远版",
          "price": "19.98万",
          "fuelType": "汽油",
          "size": "4990x1880x1455"
        },
        {
          "configName": "红旗H6 2025款 2.0T 致尚版",
          "price": "21.58万",
          "fuelType": "汽油",
          "size": "4990x1880x1455"
        },
        {
          "configName": "红旗H6 2025款 2.0T 致臻版",
          "price": "23.98万",
          "fuelType": "汽油",
          "size": "4990x1880x1455"
        },
        {
          "configName": "红旗H6 2024款 2.0T 致行版",
          "price": "17.98万",
          "fuelType": "汽油",
          "size": "4990x1880x1455"
        },
        {
          "configName": "红旗H6 2024款 2.0T 致美版",
          "price": "19.28万",
          "fuelType": "汽油",
          "size": "4990x1880x1455"
        },
        {
          "configName": "红旗H6 2024款 2.0T 致逸版",
          "price": "20.58万",
          "fuelType": "汽油",
          "size": "4990x1880x1455"
        },
        {
          "configName": "红旗H6 2024款 2.0T 致尚版",
          "price": "21.58万",
          "fuelType": "汽油",
          "size": "4990x1880x1455"
        },
        {
          "configName": "红旗H6 2024款 2.0T 致臻版",
          "price": "23.98万",
          "fuelType": "汽油",
          "size": "4990x1880x1455"
        }
      ]
    },
    {
      "carName": "红旗E-QM5",
      "mainImage": "https://p3.dcarimg.com/img/tos-cn-i-dcdx/a9472eaf9d434b729047fe8c11a5a2b2~1200x0.png",
      "seriesName": "一汽红旗/中型车",
      "configs": [
        {
          "configName": "红旗E-QM5 2025款 出租换电版",
          "price": "12.18万",
          "fuelType": "纯电动",
          "size": "5040x1910x1569"
        },
        {
          "configName": "红旗E-QM5 2025款 500KM 出租版",
          "price": "16.78万",
          "fuelType": "纯电动",
          "size": "5040x1910x1569"
        },
        {
          "configName": "红旗E-QM5 2025款 500KM 出行版",
          "price": "16.78万",
          "fuelType": "纯电动",
          "size": "5040x1910x1569"
        },
        {
          "configName": "红旗E-QM5 2025款 610KM PLUS版",
          "price": "20.18万",
          "fuelType": "纯电动",
          "size": "5040x1910x1569"
        },
        {
          "configName": "红旗E-QM5 2024款  450KM 出行版 100kW",
          "price": "16.58万",
          "fuelType": "纯电动",
          "size": "5040x1910x1569"
        },
        {
          "configName": "红旗E-QM5 2024款  500KM 出行版 100kW",
          "price": "16.78万",
          "fuelType": "纯电动",
          "size": "5040x1910x1569"
        },
        {
          "configName": "红旗E-QM5 2024款 560KM PLUS版 100kW",
          "price": "19.98万",
          "fuelType": "纯电动",
          "size": "5040x1910x1569"
        },
        {
          "configName": "红旗E-QM5 2024款 610KM PLUS版 100kW",
          "price": "20.18万",
          "fuelType": "纯电动",
          "size": "5040x1910x1569"
        },
        {
          "configName": "红旗E-QM5 2021款 换电 出租版 5座",
          "price": "23.98万",
          "fuelType": "纯电动",
          "size": "5040x1910x1569"
        }
      ]
    },
    {
      "carName": "红旗国礼",
      "mainImage": "https://p3.dcarimg.com/img/tos-cn-i-dcdx/2017d0d0fe47488b80dba8a50de81beb~1200x0.png",
      "seriesName": "一汽红旗/大型车",
      "configs": [
        {
          "configName": "红旗国礼 2024款 4.0T V8 标准版",
          "price": "718万",
          "fuelType": "汽油",
          "size": "5980x2090x1710"
        }
      ]
    },
    {
      "carName": "红旗EH7",
      "mainImage": "https://p3.dcarimg.com/img/tos-cn-i-dcdx/4eea3b8d4fb74f51a90772a6c96213da~1200x0.png",
      "seriesName": "一汽红旗/中大型车",
      "configs": [
        {
          "configName": "红旗EH7 2025款 600 智选版",
          "price": "20.88万",
          "fuelType": "纯电动",
          "size": "4980x1915x1490"
        },
        {
          "configName": "红旗EH7 2025款 690 智选版",
          "price": "21.88万",
          "fuelType": "纯电动",
          "size": "4980x1915x1490"
        },
        {
          "configName": "红旗EH7 2025款 640 四驱智选版",
          "price": "23.88万",
          "fuelType": "纯电动",
          "size": "4980x1915x1490"
        },
        {
          "configName": "红旗EH7 2025款 820 智选版",
          "price": "24.88万",
          "fuelType": "纯电动",
          "size": "4980x1915x1490"
        },
        {
          "configName": "红旗EH7 2025款 760 四驱智选版",
          "price": "28.88万",
          "fuelType": "纯电动",
          "size": "4980x1915x1490"
        },
        {
          "configName": "红旗EH7 2024款 600 Pro",
          "price": "22.98万",
          "fuelType": "纯电动",
          "size": "4980x1915x1490"
        },
        {
          "configName": "红旗EH7 2024款 600 Pro荣耀版",
          "price": "22.98万",
          "fuelType": "纯电动",
          "size": "4980x1915x1490"
        },
        {
          "configName": "红旗EH7 2024款 690 Pro",
          "price": "23.98万",
          "fuelType": "纯电动",
          "size": "4980x1915x1490"
        },
        {
          "configName": "红旗EH7 2024款 690 Pro荣耀版",
          "price": "23.98万",
          "fuelType": "纯电动",
          "size": "4980x1915x1490"
        },
        {
          "configName": "红旗EH7 2024款 640 Pro+ 四驱版",
          "price": "25.98万",
          "fuelType": "纯电动",
          "size": "4980x1915x1490"
        },
        {
          "configName": "红旗EH7 2024款 640 Pro+ 四驱版荣耀版",
          "price": "25.98万",
          "fuelType": "纯电动",
          "size": "4980x1915x1490"
        },
        {
          "configName": "红旗EH7 2024款 820 Pro",
          "price": "26.98万",
          "fuelType": "纯电动",
          "size": "4980x1915x1490"
        },
        {
          "configName": "红旗EH7 2024款 820 Pro荣耀版",
          "price": "26.98万",
          "fuelType": "纯电动",
          "size": "4980x1915x1490"
        },
        {
          "configName": "红旗EH7 2024款 760 Pro+ 四驱版",
          "price": "30.98万",
          "fuelType": "纯电动",
          "size": "4980x1915x1490"
        },
        {
          "configName": "红旗EH7 2024款 760 Pro+ 四驱版荣耀版",
          "price": "30.98万",
          "fuelType": "纯电动",
          "size": "4980x1915x1490"
        }
      ]
    },
    {
      "carName": "红旗H9",
      "mainImage": "https://p3.dcarimg.com/img/tos-cn-i-dcdx/f6878db99ae145df9966ef7aab1d0ae5~1200x0.png",
      "seriesName": "一汽红旗/中大型车",
      "configs": [
        {
          "configName": "红旗H9 2025款 2.0T 旗享 豪华商务版",
          "price": "32.98万",
          "fuelType": "48V轻混系统",
          "size": "5137x1904x1498"
        },
        {
          "configName": "红旗H9 2025款 2.0T 旗享 私享风尚版",
          "price": "32.98万",
          "fuelType": "48V轻混系统",
          "size": "5137x1904x1498"
        },
        {
          "configName": "红旗H9 2025款 2.0T 旗畅 豪华商务版",
          "price": "36.98万",
          "fuelType": "48V轻混系统",
          "size": "5137x1904x1498"
        },
        {
          "configName": "红旗H9 2025款 2.0T 旗畅 私享风尚版",
          "price": "36.98万",
          "fuelType": "48V轻混系统",
          "size": "5137x1904x1498"
        },
        {
          "configName": "红旗H9 2025款 3.0T 旗畅四驱 豪华商务版",
          "price": "45.98万",
          "fuelType": "汽油",
          "size": "5137x1904x1498"
        },
        {
          "configName": "红旗H9 2025款 3.0T 旗领四驱 豪华商务版",
          "price": "53.98万",
          "fuelType": "汽油",
          "size": "5137x1904x1498"
        },
        {
          "configName": "红旗H9 2025款 3.0T 旗领四驱 私享风尚版",
          "price": "53.98万",
          "fuelType": "汽油",
          "size": "5137x1904x1498"
        },
        {
          "configName": "红旗H9 2024款 2.0T 旗享 豪华商务版",
          "price": "32.98万",
          "fuelType": "48V轻混系统",
          "size": "5137x1904x1498"
        },
        {
          "configName": "红旗H9 2024款 2.0T 旗享 私享风尚版",
          "price": "32.98万",
          "fuelType": "48V轻混系统",
          "size": "5137x1904x1498"
        },
        {
          "configName": "红旗H9 2024款 2.0T 旗畅 豪华商务版",
          "price": "36.98万",
          "fuelType": "48V轻混系统",
          "size": "5137x1904x1498"
        },
        {
          "configName": "红旗H9 2024款 2.0T 旗畅 私享风尚版",
          "price": "36.98万",
          "fuelType": "48V轻混系统",
          "size": "5137x1904x1498"
        },
        {
          "configName": "红旗H9 2024款 3.0T 旗畅 豪华商务版",
          "price": "45.98万",
          "fuelType": "汽油",
          "size": "5137x1904x1498"
        },
        {
          "configName": "红旗H9 2024款 3.0T 旗领四驱 豪华商务版",
          "price": "53.98万",
          "fuelType": "汽油",
          "size": "5137x1904x1498"
        },
        {
          "configName": "红旗H9 2024款 3.0T 旗领四驱 私享风尚版",
          "price": "53.98万",
          "fuelType": "汽油",
          "size": "5137x1904x1498"
        }
      ]
    },
    {
      "carName": "红旗国雅",
      "mainImage": "https://p3.dcarimg.com/img/tos-cn-i-dcdx/ca785f1b2a9d47ee83f4aeab657bb7a1~1200x0.png",
      "seriesName": "一汽红旗/大型车",
      "configs": [
        {
          "configName": "红旗国雅 2024款 3.0T V6版",
          "price": "140万",
          "fuelType": "油电混合",
          "size": "5353x1998x1511"
        },
        {
          "configName": "红旗国雅 2024款 4.0T V8版",
          "price": "186万",
          "fuelType": "油电混合",
          "size": "5353x1998x1511"
        }
      ]
    },
    {
      "carName": "红旗HS3",
      "mainImage": "https://p3.dcarimg.com/img/tos-cn-i-dcdx/80174b63927b4f498f772d60c2afa08b~1200x0.png",
      "seriesName": "一汽红旗/紧凑型SUV",
      "configs": [
        {
          "configName": "红旗HS3 2024款 1.5T 勇为版",
          "price": "14.58万",
          "fuelType": "汽油",
          "size": "4655x1900x1668"
        },
        {
          "configName": "红旗HS3 2024款 1.5T 志为版",
          "price": "14.98万",
          "fuelType": "汽油",
          "size": "4655x1900x1668"
        },
        {
          "configName": "红旗HS3 2024款 1.5T 善为版",
          "price": "15.98万",
          "fuelType": "汽油",
          "size": "4655x1900x1668"
        },
        {
          "configName": "红旗HS3 2024款 2.0T 可为版",
          "price": "17.28万",
          "fuelType": "汽油",
          "size": "4655x1900x1668"
        }
      ]
    },
    {
      "carName": "红旗天工06",
      "mainImage": "https://p3.dcarimg.com/img/tos-cn-i-dcdx/a160ac5ee8cf4a069cc4210d25ba0c02~1200x0.png",
      "seriesName": "一汽红旗/中型SUV",
      "configs": [
        {
          "configName": "红旗天工06 2025款 520版",
          "price": "17.98万",
          "fuelType": "纯电动",
          "size": "4750x1900x1640"
        },
        {
          "configName": "红旗天工06 2025款 520 智选版",
          "price": "18.98万",
          "fuelType": "纯电动",
          "size": "4750x1900x1640"
        },
        {
          "configName": "红旗天工06 2025款 700版",
          "price": "19.58万",
          "fuelType": "纯电动",
          "size": "4750x1900x1640"
        },
        {
          "configName": "红旗天工06 2025款 700 智选版",
          "price": "20.58万",
          "fuelType": "纯电动",
          "size": "4750x1900x1640"
        },
        {
          "configName": "红旗天工06 2025款 660 四驱版",
          "price": "21.58万",
          "fuelType": "纯电动",
          "size": "4750x1900x1640"
        },
        {
          "configName": "红旗天工06 2025款 660 四驱智选版",
          "price": "22.58万",
          "fuelType": "纯电动",
          "size": "4750x1900x1640"
        }
      ]
    },
    {
      "carName": "红旗HS3 PHEV",
      "mainImage": "https://p3.dcarimg.com/img/tos-cn-i-dcdx/597fa893caaf4d34b8ebf22618504521~1200x0.png",
      "seriesName": "一汽红旗/紧凑型SUV",
      "configs": [
        {
          "configName": "红旗HS3 PHEV 2025款 117km 劲为PLUS版",
          "price": "16.18万",
          "fuelType": "插电式混合动力",
          "size": "4655x1900x1668"
        },
        {
          "configName": "红旗HS3 PHEV 2024款 改款 115km 劲为版",
          "price": "15.98万",
          "fuelType": "插电式混合动力",
          "size": "4655x1900x1668"
        }
      ]
    },
    {
      "carName": "红旗HS7 PHEV",
      "mainImage": "https://p3.dcarimg.com/img/tos-cn-i-dcdx/4a3b8d8f97f547bb9d1385a2608561dc~1200x0.png",
      "seriesName": "一汽红旗/中大型SUV",
      "configs": [
        {
          "configName": "红旗HS7 PHEV 2024款 2.0T 两驱旗享版 6座",
          "price": "29.08万",
          "fuelType": "插电式混合动力",
          "size": "4995x1960x1760"
        },
        {
          "configName": "红旗HS7 PHEV 2024款 2.0T 两驱旗享版 7座",
          "price": "29.08万",
          "fuelType": "插电式混合动力",
          "size": "4995x1960x1760"
        },
        {
          "configName": "红旗HS7 PHEV 2024款 2.0T 四驱旗畅版 6座",
          "price": "31.58万",
          "fuelType": "插电式混合动力",
          "size": "4995x1960x1760"
        },
        {
          "configName": "红旗HS7 PHEV 2024款 2.0T 四驱旗畅版 7座",
          "price": "31.58万",
          "fuelType": "插电式混合动力",
          "size": "4995x1960x1760"
        },
        {
          "configName": "红旗HS7 PHEV 2024款 2.0T 四驱旗领版 6座",
          "price": "34.58万",
          "fuelType": "插电式混合动力",
          "size": "4995x1960x1760"
        },
        {
          "configName": "红旗HS7 PHEV 2024款 2.0T 四驱旗领版 7座",
          "price": "34.58万",
          "fuelType": "插电式混合动力",
          "size": "4995x1960x1760"
        }
      ]
    },
    {
      "carName": "红旗HS5",
      "mainImage": "https://p3.dcarimg.com/img/tos-cn-i-dcdx/cfd801560d8c4325861b777648232132~1200x0.png",
      "seriesName": "一汽红旗/中型SUV",
      "configs": [
        {
          "configName": "红旗HS5 2025款 2.0T 旗悦Pro版",
          "price": "18.38万",
          "fuelType": "汽油",
          "size": "4785x1905x1700"
        },
        {
          "configName": "红旗HS5 2025款 2.0T 60万辆纪念版",
          "price": "18.68万",
          "fuelType": "汽油",
          "size": "4785x1905x1700"
        },
        {
          "configName": "红旗HS5 2025款 2.0T 旗享Pro版",
          "price": "19.98万",
          "fuelType": "汽油",
          "size": "4785x1905x1700"
        },
        {
          "configName": "红旗HS5 2025款 2.0T 两驱玄影版",
          "price": "20.38万",
          "fuelType": "汽油",
          "size": "4785x1905x1700"
        },
        {
          "configName": "红旗HS5 2025款 2.0T 四驱旗享Pro版",
          "price": "21.38万",
          "fuelType": "汽油",
          "size": "4785x1905x1700"
        },
        {
          "configName": "红旗HS5 2025款 2.0T 四驱玄影版",
          "price": "21.68万",
          "fuelType": "汽油",
          "size": "4785x1905x1700"
        },
        {
          "configName": "红旗HS5 2025款 2.0T 旗领Pro版",
          "price": "22.68万",
          "fuelType": "汽油",
          "size": "4785x1905x1700"
        },
        {
          "configName": "红旗HS5 2025款 2.0T 四驱旗领Pro版",
          "price": "24.98万",
          "fuelType": "汽油",
          "size": "4785x1905x1700"
        }
      ]
    },
    {
      "carName": "红旗HS7",
      "mainImage": "https://p3.dcarimg.com/img/tos-cn-i-dcdx/1e68869a01ba46c0b5837dbdaef03b86~1200x0.png",
      "seriesName": "一汽红旗/中大型SUV",
      "configs": [
        {
          "configName": "红旗HS7 2024款 2.0T 自动两驱旗悦版 5座",
          "price": "25.58万",
          "fuelType": "48V轻混系统",
          "size": "4995x1960x1760"
        },
        {
          "configName": "红旗HS7 2024款 2.0T 自动四驱旗享版 6座",
          "price": "28.58万",
          "fuelType": "48V轻混系统",
          "size": "4995x1960x1760"
        },
        {
          "configName": "红旗HS7 2024款 2.0T 自动四驱旗享版 7座",
          "price": "28.58万",
          "fuelType": "48V轻混系统",
          "size": "4995x1960x1760"
        },
        {
          "configName": "红旗HS7 2023款 2.0T 自动两驱旗悦版 5座",
          "price": "25.58万",
          "fuelType": "48V轻混系统",
          "size": "4995x1960x1760"
        },
        {
          "configName": "红旗HS7 2023款 2.0T 自动两驱旗享版 6座",
          "price": "29.58万",
          "fuelType": "48V轻混系统",
          "size": "4995x1960x1760"
        },
        {
          "configName": "红旗HS7 2023款 2.0T 自动两驱旗享版 7座",
          "price": "29.58万",
          "fuelType": "48V轻混系统",
          "size": "4995x1960x1760"
        },
        {
          "configName": "红旗HS7 2023款 2.0T 四驱旗畅版 6座",
          "price": "30.58万",
          "fuelType": "48V轻混系统",
          "size": "4995x1960x1760"
        },
        {
          "configName": "红旗HS7 2023款 2.0T 四驱旗畅版 7座",
          "price": "30.58万",
          "fuelType": "48V轻混系统",
          "size": "4995x1960x1760"
        },
        {
          "configName": "红旗HS7 2023款 2.0T 四驱旗领版 6座",
          "price": "33.58万",
          "fuelType": "48V轻混系统",
          "size": "4995x1960x1760"
        },
        {
          "configName": "红旗HS7 2023款 2.0T 四驱旗领版 7座",
          "price": "33.58万",
          "fuelType": "48V轻混系统",
          "size": "4995x1960x1760"
        }
      ]
    },
    {
      "carName": "红旗天工08",
      "mainImage": "https://p3.dcarimg.com/img/tos-cn-i-dcdx/09fc8d1a15fe4528a3f5e677e6337ea7~1200x0.png",
      "seriesName": "一汽红旗/中大型SUV",
      "configs": [
        {
          "configName": "红旗天工08 2025款 605 后驱先锋版",
          "price": "21.59万",
          "fuelType": "纯电动",
          "size": "4925x1950x1680"
        },
        {
          "configName": "红旗天工08 2025款 520 Max后驱版",
          "price": "23.98万",
          "fuelType": "纯电动",
          "size": "4925x1950x1680"
        },
        {
          "configName": "红旗天工08 2025款 605 Max后驱版",
          "price": "24.98万",
          "fuelType": "纯电动",
          "size": "4925x1950x1680"
        },
        {
          "configName": "红旗天工08 2025款 730 Max后驱版",
          "price": "30.98万",
          "fuelType": "纯电动",
          "size": "4925x1950x1680"
        },
        {
          "configName": "红旗天工08 2025款 565 四驱先锋版",
          "price": "24.59万",
          "fuelType": "纯电动",
          "size": "4925x1950x1680"
        },
        {
          "configName": "红旗天工08 2025款 565 Ultra四驱版",
          "price": "27.98万",
          "fuelType": "纯电动",
          "size": "4925x1950x1680"
        },
        {
          "configName": "红旗天工08 2025款 680 Ultra四驱版",
          "price": "33.98万",
          "fuelType": "纯电动",
          "size": "4925x1950x1680"
        },
        {
          "configName": "红旗天工08 2025款 605 后驱智选版",
          "price": "24.98万",
          "fuelType": "纯电动",
          "size": "4925x1950x1680"
        },
        {
          "configName": "红旗天工08 2025款 730 后驱智选版",
          "price": "30.98万",
          "fuelType": "纯电动",
          "size": "4925x1950x1680"
        },
        {
          "configName": "红旗天工08 2025款 565 四驱智选版",
          "price": "27.98万",
          "fuelType": "纯电动",
          "size": "4925x1950x1680"
        },
        {
          "configName": "红旗天工08 2025款 680 四驱智选版",
          "price": "33.98万",
          "fuelType": "纯电动",
          "size": "4925x1950x1680"
        }
      ]
    },
    {
      "carName": "红旗HQ9",
      "mainImage": "https://p3.dcarimg.com/img/tos-cn-i-dcdx/d34ad45b227740dc854984d98e8d2a1b~1200x0.png",
      "seriesName": "一汽红旗/中大型MPV",
      "configs": [
        {
          "configName": "红旗HQ9 2024款 公务版",
          "price": "34.88万",
          "fuelType": "48V轻混系统",
          "size": "5222x2005x1935"
        },
        {
          "configName": "红旗HQ9 2024款 商务版",
          "price": "35.88万",
          "fuelType": "48V轻混系统",
          "size": "5222x2005x1935"
        },
        {
          "configName": "红旗HQ9 2024款 豪华版",
          "price": "43.88万",
          "fuelType": "48V轻混系统",
          "size": "5222x2005x1935"
        },
        {
          "configName": "红旗HQ9 2024款 豪华版福祉版",
          "price": "47.88万",
          "fuelType": "48V轻混系统",
          "size": "5222x2005x1935"
        },
        {
          "configName": "红旗HQ9 2024款 旗舰版",
          "price": "53.88万",
          "fuelType": "48V轻混系统",
          "size": "5222x2005x1935"
        },
        {
          "configName": "红旗HQ9 2024款 旗舰版福祉版",
          "price": "57.88万",
          "fuelType": "48V轻混系统",
          "size": "5222x2005x1935"
        }
      ]
    },
    {
      "carName": "红旗E-HS9",
      "mainImage": "https://p3.dcarimg.com/img/tos-cn-i-dcdx/3da2d0b0553e45c5a4b8341fa7a7f207~1200x0.png",
      "seriesName": "一汽红旗/大型SUV",
      "configs": [
        {
          "configName": "红旗E-HS9 2024款 690km 旗悦版 七座",
          "price": "58.98万",
          "fuelType": "纯电动",
          "size": "5209x2010x1731"
        },
        {
          "configName": "红旗E-HS9 2024款 690km 旗享版 六座",
          "price": "61.98万",
          "fuelType": "纯电动",
          "size": "5209x2010x1731"
        },
        {
          "configName": "红旗E-HS9 2024款 660km 旗畅版 六座",
          "price": "68.98万",
          "fuelType": "纯电动",
          "size": "5209x2010x1713"
        },
        {
          "configName": "红旗E-HS9 2024款 660km 旗领版 四座",
          "price": "77.98万",
          "fuelType": "纯电动",
          "size": "5209x2010x1713"
        },
        {
          "configName": "红旗E-HS9 2022款 改款 460km 旗悦版 七座",
          "price": "50.98万",
          "fuelType": "纯电动",
          "size": "5209x2010x1731"
        },
        {
          "configName": "红旗E-HS9 2022款 改款 460km 旗享版 六座",
          "price": "53.98万",
          "fuelType": "纯电动",
          "size": "5209x2010x1731"
        },
        {
          "configName": "红旗E-HS9 2022款 改款 510km 旗畅版 六座",
          "price": "63.98万",
          "fuelType": "纯电动",
          "size": "5209x2010x1713"
        },
        {
          "configName": "红旗E-HS9 2022款 改款 510km 旗领版 四座",
          "price": "72.98万",
          "fuelType": "纯电动",
          "size": "5209x2010x1713"
        }
      ]
    },
    {
      "carName": "红旗国耀",
      "mainImage": "https://p3.dcarimg.com/img/tos-cn-i-dcdx/547304f0e768411e817090d21f47b489~1200x0.png",
      "seriesName": "一汽红旗/大型SUV",
      "configs": [
        {
          "configName": "红旗国耀 2022款 4.0T 6座典雅旗航版",
          "price": "136.58万",
          "fuelType": "汽油",
          "size": "5695x2095x1985"
        },
        {
          "configName": "红旗国耀 2022款 4.0T 4座尊爵旗舰版",
          "price": "146.58万",
          "fuelType": "汽油",
          "size": "5695x2095x1985"
        }
      ]
    },
    {
      "carName": "红旗HQ9 PHEV",
      "mainImage": "https://p3.dcarimg.com/img/tos-cn-i-dcdx/8ccf04ce60974d8f8aae2c209ac64d95~1200x0.png",
      "seriesName": "一汽红旗/中大型MPV",
      "configs": [
        {
          "configName": "红旗HQ9 PHEV 2024款 四驱商务版",
          "price": "35.88万",
          "fuelType": "插电式混合动力",
          "size": "5222x2005x1935"
        },
        {
          "configName": "红旗HQ9 PHEV 2024款 四驱商务版福祉版",
          "price": "39.88万",
          "fuelType": "插电式混合动力",
          "size": "5222x2005x1935"
        },
        {
          "configName": "红旗HQ9 PHEV 2024款 四驱豪华版",
          "price": "43.88万",
          "fuelType": "插电式混合动力",
          "size": "5222x2005x1935"
        },
        {
          "configName": "红旗HQ9 PHEV 2024款 四驱旗舰版",
          "price": "53.88万",
          "fuelType": "插电式混合动力",
          "size": "5222x2005x1935"
        }
      ]
    }
  ]
}